{"_id":"5da73caceb6336f3185c3598","page":0,"fullpage":true,"headline":"","date":"2004-01-22T14:36:50.995Z","content":"\n\n    \n        \n            ABC\n            \n\n                Edición PDF\n\n                Navegar por fecha\n                Ir a ABC.es\n            \t\t\t\t\t\n        \n        ABC de Sevilla\n        ABC de Córdoba\n    \n\n    \n\n    \n    \n\nAvanzar o retroceder por resultado de búsqueda1/1Avanzar o retroceder por las páginas del periódicoPrimeroAnteriorPág. 29/108SiguienteÚltimoAvanzar o retroceder por díaAnteriorMadrid, 22 deEnero de 2004SiguienteDescargar esta página en PDFAñadir a mi dossierQuitar de mi dossierinit('0004869076');Enviar a un amigoENLAZARE-mail del remitenteE-mail del destinatarioComentarioURL directa a la página:Insertar en un blog:URL directa a la página:ABC \n\n\n\nJUEVES 22 1 2004 \n\n\n\nInternacional 29 \n\n\n\nVarios ministros iraníes presentan su dimisión para presionar a los inmovilistas \n\nJatamí subraya desde Suiza que, por ahora, no tiene la intención de abandonar su puesto \n\nb La dimisión presentada ayer por varios ministros no es equivalente a su renuncia automática, ya que los dimisionarios aún esperan que los conservadores rectifiquen ABC TEHERÁN. Los reformistas iraníes han aumentado la presión sobre sus adversarios inmovilistas después de que varios ministros presentasen ayer su dimisión para protestar por la decisión de impedir que un alto número de candidatos liberales se presenten a las próximas elecciones del 20 de febrero. La ola de dimisiones, sin embargo, no llega hasta el presidente, Mohamed Jatamí, quien desmintió los rumores de su presunto abandono del cargo e incluso auguró una próxima solución de la crisis que permitiría la celebración de elecciones libres. Tengo la intención de continuar con mi labor y servicio al pueblo declaró en Suiza donde ha mantenido diversas reuniones con autoridades helvéticas. La dimisión colectiva de varios ministros fue anunciada por el vicepresidente iraní, Mohammed Alí Abtaji, quien fue también quien llegó a evocar la posibilidad de que el propio Jatamí pudiese presentar su renuncia. Abtaji \n\n\n\nrecordó las antiguas amenazas de Jatamí y subvrayó que un cierto número de ministros y vicepresidentes han dimitido Pero, a la vez, dio a entender que la presentación de la dimisión no es equivalente a su renuncia automática. Explicó a este respecto que, antes de hacer efectiva su salida del Gobierno, los dimisionarios esperarán el resultado de las deliberaciones mantenidas por el Consejo de guardianes de la Constitución, núcleo duro de los inmovilistas. Se trata, por tanto, de unas dimisiones condicionadas, o en suspenso, pero que sirven para aumentar la presión sobre el Consejo de guardianes en el pulso que ortodoxos y liberales mantienen ante los próximos comicios. Abtahi reiteró la amenaza lanzada la pasada semana por Jatamí de una dimisión en bloque de todos los reformistas que controlan la Presidencia y el Ejecutivo iraní si el Consejo de guardianes no da marcha atrás a su decisión de veto colectivo. Cuando así ocurra, aquí todo el mundo se iría afirmó entonces el presidente, quien, sin embargo, ayer insistió en que, pese a todo, él sigue todavía en su puesto. El Consejo de guardianes ha anulado casi la mitad de las candidaturas electorales en una decisión que los reformistas tildan de golpe de Estado \n\n\n\nEl científico David Kelly declaró antes de suicidarse que Irak tenía armas de destrucción masiva \n\nEMILI J. BLASCO. CORRESPONSAL LONDRES. A una semana de la publicación del informe Hutton, la BBC difundió anoche una entrevista nunca emitida en la que el experto de armas David Kelly aseguraba que Irak era una amenaza inmediata y confirmaba que Sadam Husein tenía armas de destrucción masiva. El suicidio de Kelly tras la acusación lanzada por la BBC de que Tony Blair exageró el riesto que suponía Irak abrieron una crisis política cuyas dimensiones debería marcar el informe del juez Hutton. El documental de Panorama emitido anoche pareció reforzar ciertos aspectos de la posición del Gobierno, aunque tampoco le dio toda la razón, al tiempo que censuraba algunos comportamientos de la BBC en un ejercicio de pluralidad interna difícilmente imaginable en otras radiotelevisiones públicas. La emisión fue elaborada por la redacción de programas informativos de la BBC en lo que algunos comentaristas han visto una batalla interna con- \n\n\n\ntra la redacción de informativos diarios, de la que formaba parte el programa Today de Andrew Gilligan, desencadenante de la polémica. La entrevista con Kelly fue realizada en octubre de 2002, un mes después de que Blair presentara el polémico informe en el que se aseguraba que Irak suponía un riesgo para la paz y podía emplear sus armas de destrucción masiva en apenas 45 minutos. En esa entrevista, cuya no difusión en todo este tiempo no ha sido justificada por la dirección de la BBC, Kelly daba la razón al Gobierno en el sentido de que Sadam era una amenaza inmediata pero venía a negar que estuviera en disposición de sus armas de destrucción masiva en 45 minutos, ya que en su opinión éstas sólo podían estar operativas en cuestión de días o semanas El programa llegó a afirmar que Gilligan estaba equivocado cuando dijo que Downing Street ordenó a los servicios de inteligencia que exagerasen los datos. \n\n\n\n\nDescargar esta página en PDFAñadir a mi dossierQuitar de mi dossierinit('0004869076');Enviar a un amigoENLAZARE-mail del remitenteE-mail del destinatarioComentarioURL directa a la página:Insertar en un blog:URL directa a la página:ABC \n\n\n\nJUEVES 22 1 2004 \n\n\n\nInternacional 29 \n\n\n\nVarios ministros iraníes presentan su dimisión para presionar a los inmovilistas \n\nJatamí subraya desde Suiza que, por ahora, no tiene la intención de abandonar su puesto \n\nb La dimisión presentada ayer por varios ministros no es equivalente a su renuncia automática, ya que los dimisionarios aún esperan que los conservadores rectifiquen ABC TEHERÁN. Los reformistas iraníes han aumentado la presión sobre sus adversarios inmovilistas después de que varios ministros presentasen ayer su dimisión para protestar por la decisión de impedir que un alto número de candidatos liberales se presenten a las próximas elecciones del 20 de febrero. La ola de dimisiones, sin embargo, no llega hasta el presidente, Mohamed Jatamí, quien desmintió los rumores de su presunto abandono del cargo e incluso auguró una próxima solución de la crisis que permitiría la celebración de elecciones libres. Tengo la intención de continuar con mi labor y servicio al pueblo declaró en Suiza donde ha mantenido diversas reuniones con autoridades helvéticas. La dimisión colectiva de varios ministros fue anunciada por el vicepresidente iraní, Mohammed Alí Abtaji, quien fue también quien llegó a evocar la posibilidad de que el propio Jatamí pudiese presentar su renuncia. Abtaji \n\n\n\nrecordó las antiguas amenazas de Jatamí y subvrayó que un cierto número de ministros y vicepresidentes han dimitido Pero, a la vez, dio a entender que la presentación de la dimisión no es equivalente a su renuncia automática. Explicó a este respecto que, antes de hacer efectiva su salida del Gobierno, los dimisionarios esperarán el resultado de las deliberaciones mantenidas por el Consejo de guardianes de la Constitución, núcleo duro de los inmovilistas. Se trata, por tanto, de unas dimisiones condicionadas, o en suspenso, pero que sirven para aumentar la presión sobre el Consejo de guardianes en el pulso que ortodoxos y liberales mantienen ante los próximos comicios. Abtahi reiteró la amenaza lanzada la pasada semana por Jatamí de una dimisión en bloque de todos los reformistas que controlan la Presidencia y el Ejecutivo iraní si el Consejo de guardianes no da marcha atrás a su decisión de veto colectivo. Cuando así ocurra, aquí todo el mundo se iría afirmó entonces el presidente, quien, sin embargo, ayer insistió en que, pese a todo, él sigue todavía en su puesto. El Consejo de guardianes ha anulado casi la mitad de las candidaturas electorales en una decisión que los reformistas tildan de golpe de Estado \n\n\n\nEl científico David Kelly declaró antes de suicidarse que Irak tenía armas de destrucción masiva \n\nEMILI J. BLASCO. CORRESPONSAL LONDRES. A una semana de la publicación del informe Hutton, la BBC difundió anoche una entrevista nunca emitida en la que el experto de armas David Kelly aseguraba que Irak era una amenaza inmediata y confirmaba que Sadam Husein tenía armas de destrucción masiva. El suicidio de Kelly tras la acusación lanzada por la BBC de que Tony Blair exageró el riesto que suponía Irak abrieron una crisis política cuyas dimensiones debería marcar el informe del juez Hutton. El documental de Panorama emitido anoche pareció reforzar ciertos aspectos de la posición del Gobierno, aunque tampoco le dio toda la razón, al tiempo que censuraba algunos comportamientos de la BBC en un ejercicio de pluralidad interna difícilmente imaginable en otras radiotelevisiones públicas. La emisión fue elaborada por la redacción de programas informativos de la BBC en lo que algunos comentaristas han visto una batalla interna con- \n\n\n\ntra la redacción de informativos diarios, de la que formaba parte el programa Today de Andrew Gilligan, desencadenante de la polémica. La entrevista con Kelly fue realizada en octubre de 2002, un mes después de que Blair presentara el polémico informe en el que se aseguraba que Irak suponía un riesgo para la paz y podía emplear sus armas de destrucción masiva en apenas 45 minutos. En esa entrevista, cuya no difusión en todo este tiempo no ha sido justificada por la dirección de la BBC, Kelly daba la razón al Gobierno en el sentido de que Sadam era una amenaza inmediata pero venía a negar que estuviera en disposición de sus armas de destrucción masiva en 45 minutos, ya que en su opinión éstas sólo podían estar operativas en cuestión de días o semanas El programa llegó a afirmar que Gilligan estaba equivocado cuando dijo que Downing Street ordenó a los servicios de inteligencia que exagerasen los datos. \n\n\n\n\nABC \n\n\n\nJUEVES 22 1 2004 \n\n\n\nInternacional 29 \n\n\n\nVarios ministros iraníes presentan su dimisión para presionar a los inmovilistas \n\nJatamí subraya desde Suiza que, por ahora, no tiene la intención de abandonar su puesto \n\nb La dimisión presentada ayer por varios ministros no es equivalente a su renuncia automática, ya que los dimisionarios aún esperan que los conservadores rectifiquen ABC TEHERÁN. Los reformistas iraníes han aumentado la presión sobre sus adversarios inmovilistas después de que varios ministros presentasen ayer su dimisión para protestar por la decisión de impedir que un alto número de candidatos liberales se presenten a las próximas elecciones del 20 de febrero. La ola de dimisiones, sin embargo, no llega hasta el presidente, Mohamed Jatamí, quien desmintió los rumores de su presunto abandono del cargo e incluso auguró una próxima solución de la crisis que permitiría la celebración de elecciones libres. Tengo la intención de continuar con mi labor y servicio al pueblo declaró en Suiza donde ha mantenido diversas reuniones con autoridades helvéticas. La dimisión colectiva de varios ministros fue anunciada por el vicepresidente iraní, Mohammed Alí Abtaji, quien fue también quien llegó a evocar la posibilidad de que el propio Jatamí pudiese presentar su renuncia. Abtaji \n\n\n\nrecordó las antiguas amenazas de Jatamí y subvrayó que un cierto número de ministros y vicepresidentes han dimitido Pero, a la vez, dio a entender que la presentación de la dimisión no es equivalente a su renuncia automática. Explicó a este respecto que, antes de hacer efectiva su salida del Gobierno, los dimisionarios esperarán el resultado de las deliberaciones mantenidas por el Consejo de guardianes de la Constitución, núcleo duro de los inmovilistas. Se trata, por tanto, de unas dimisiones condicionadas, o en suspenso, pero que sirven para aumentar la presión sobre el Consejo de guardianes en el pulso que ortodoxos y liberales mantienen ante los próximos comicios. Abtahi reiteró la amenaza lanzada la pasada semana por Jatamí de una dimisión en bloque de todos los reformistas que controlan la Presidencia y el Ejecutivo iraní si el Consejo de guardianes no da marcha atrás a su decisión de veto colectivo. Cuando así ocurra, aquí todo el mundo se iría afirmó entonces el presidente, quien, sin embargo, ayer insistió en que, pese a todo, él sigue todavía en su puesto. El Consejo de guardianes ha anulado casi la mitad de las candidaturas electorales en una decisión que los reformistas tildan de golpe de Estado \n\n\n\nEl científico David Kelly declaró antes de suicidarse que Irak tenía armas de destrucción masiva \n\nEMILI J. BLASCO. CORRESPONSAL LONDRES. A una semana de la publicación del informe Hutton, la BBC difundió anoche una entrevista nunca emitida en la que el experto de armas David Kelly aseguraba que Irak era una amenaza inmediata y confirmaba que Sadam Husein tenía armas de destrucción masiva. El suicidio de Kelly tras la acusación lanzada por la BBC de que Tony Blair exageró el riesto que suponía Irak abrieron una crisis política cuyas dimensiones debería marcar el informe del juez Hutton. El documental de Panorama emitido anoche pareció reforzar ciertos aspectos de la posición del Gobierno, aunque tampoco le dio toda la razón, al tiempo que censuraba algunos comportamientos de la BBC en un ejercicio de pluralidad interna difícilmente imaginable en otras radiotelevisiones públicas. La emisión fue elaborada por la redacción de programas informativos de la BBC en lo que algunos comentaristas han visto una batalla interna con- \n\n\n\ntra la redacción de informativos diarios, de la que formaba parte el programa Today de Andrew Gilligan, desencadenante de la polémica. La entrevista con Kelly fue realizada en octubre de 2002, un mes después de que Blair presentara el polémico informe en el que se aseguraba que Irak suponía un riesgo para la paz y podía emplear sus armas de destrucción masiva en apenas 45 minutos. En esa entrevista, cuya no difusión en todo este tiempo no ha sido justificada por la dirección de la BBC, Kelly daba la razón al Gobierno en el sentido de que Sadam era una amenaza inmediata pero venía a negar que estuviera en disposición de sus armas de destrucción masiva en 45 minutos, ya que en su opinión éstas sólo podían estar operativas en cuestión de días o semanas El programa llegó a afirmar que Gilligan estaba equivocado cuando dijo que Downing Street ordenó a los servicios de inteligencia que exagerasen los datos. \n\n\n\n","url":"http://hemeroteca.abc.es/nav/Navigate.exe/hemeroteca/madrid/abc/2004/01/22/029","newspaper":"abc","scraper_id":"scraper_home","id":"24777892-4f10-4c88-63df-8048297adec8","sentiment_analysis_obj":{"score":-150,"comparative":-0.07,"tokens":[{"value":"abc","negate":false},{"value":"edición","negate":false},{"value":"pdf","negate":false},{"value":"navegar","negate":false},{"value":"por","negate":false},{"value":"fecha","negate":false},{"value":"ir","negate":false},{"value":"a","negate":false},{"value":"abc","negate":false},{"value":"es","negate":false},{"value":"abc","negate":false},{"value":"de","negate":false},{"value":"sevilla","negate":false},{"value":"abc","negate":false},{"value":"de","negate":false},{"value":"córdoba","negate":false},{"value":"avanzar","negate":false},{"value":"o","negate":false},{"value":"retroceder","negate":false},{"value":"por","negate":false},{"value":"resultado","negate":false},{"value":"de","negate":false},{"value":"búsqueda1","negate":false},{"value":"1","negate":false},{"value":"avanzar","negate":false},{"value":"o","negate":false},{"value":"retroceder","negate":false},{"value":"por","negate":false},{"value":"las","negate":false},{"value":"páginas","negate":false},{"value":"del","negate":false},{"value":"periódicoprimeroanteriorpág","negate":false},{"value":"29","negate":false},{"value":"108","negate":false},{"value":"siguienteúltimoavanzar","negate":false},{"value":"o","negate":false},{"value":"retroceder","negate":false},{"value":"por","negate":false},{"value":"díaanteriormadrid","negate":false},{"value":"22","negate":false},{"value":"deenero","negate":false},{"value":"de","negate":false},{"value":"2004","negate":false},{"value":"siguientedescargar","negate":false},{"value":"esta","negate":false},{"value":"página","negate":false},{"value":"en","negate":false},{"value":"pdfañadir","negate":false},{"value":"a","negate":false},{"value":"mi","negate":false},{"value":"dossierquitar","negate":false},{"value":"de","negate":false},{"value":"mi","negate":false},{"value":"dossierinit","negate":false},{"value":"'0004869076'","negate":false},{"value":"enviar","negate":false},{"value":"a","negate":false},{"value":"un","negate":false},{"value":"amigoenlazare-mail","negate":false},{"value":"del","negate":false},{"value":"remitentee-mail","negate":false},{"value":"del","negate":false},{"value":"destinatariocomentariourl","negate":false},{"value":"directa","negate":false},{"value":"a","negate":false},{"value":"la","negate":false},{"value":"página","negate":false},{"value":"insertar","negate":false},{"value":"en","negate":false},{"value":"un","negate":false},{"value":"blog","negate":false},{"value":"url","negate":false},{"value":"directa","negate":false},{"value":"a","negate":false},{"value":"la","negate":false},{"value":"página","negate":false},{"value":"abc","negate":false},{"value":"jueves","negate":false},{"value":"22","negate":false},{"value":"1","negate":false},{"value":"2004","negate":false},{"value":"internacional","negate":false},{"value":"29","negate":false},{"value":"varios","negate":false},{"value":"ministros","negate":false},{"value":"iraníes","negate":false},{"value":"presentan","negate":false},{"value":"su","negate":false},{"value":"dimisión","negate":false},{"value":"para","negate":false},{"value":"presionar","negate":false},{"value":"a","negate":false},{"value":"los","negate":false},{"value":"inmovilistas","negate":false},{"value":"jatamí","negate":false},{"value":"subraya","negate":false},{"value":"desde","negate":false},{"value":"suiza","negate":false},{"value":"que","negate":false},{"value":"por","negate":false},{"value":"ahora","negate":false},{"value":"no","negate":true},{"value":"tiene","negate":false},{"value":"la","negate":false},{"value":"intención","negate":false},{"value":"de","negate":false},{"value":"abandonar","negate":false},{"value":"su","negate":false},{"value":"puesto","negate":false},{"value":"b","negate":false},{"value":"la","negate":false},{"value":"dimisión","negate":false},{"value":"presentada","negate":false},{"value":"ayer","negate":false},{"value":"por","negate":false},{"value":"varios","negate":false},{"value":"ministros","negate":false},{"value":"no","negate":true},{"value":"es","negate":false},{"value":"equivalente","negate":false},{"value":"a","negate":false},{"value":"su","negate":false},{"value":"renuncia","negate":false},{"value":"automática","negate":false},{"value":"ya","negate":false},{"value":"que","negate":false},{"value":"los","negate":false},{"value":"dimisionarios","negate":false},{"value":"aún","negate":false},{"value":"esperan","negate":false},{"value":"que","negate":false},{"value":"los","negate":false},{"value":"conservadores","negate":false},{"value":"rectifiquen","negate":false},{"value":"abc","negate":false},{"value":"teherán","negate":false},{"value":"los","negate":false},{"value":"reformistas","negate":false},{"value":"iraníes","negate":false},{"value":"han","negate":false},{"value":"aumentado","negate":false},{"value":"la","negate":false},{"value":"presión","negate":false},{"value":"sobre","negate":false},{"value":"sus","negate":false},{"value":"adversarios","negate":false},{"value":"inmovilistas","negate":false},{"value":"después","negate":false},{"value":"de","negate":false},{"value":"que","negate":false},{"value":"varios","negate":false},{"value":"ministros","negate":false},{"value":"presentasen","negate":false},{"value":"ayer","negate":false},{"value":"su","negate":false},{"value":"dimisión","negate":false},{"value":"para","negate":false},{"value":"protestar","negate":false},{"value":"por","negate":false},{"value":"la","negate":false},{"value":"decisión","negate":false},{"value":"de","negate":false},{"value":"impedir","negate":false},{"value":"que","negate":false},{"value":"un","negate":false},{"value":"alto","negate":false},{"value":"número","negate":false},{"value":"de","negate":false},{"value":"candidatos","negate":false},{"value":"liberales","negate":false},{"value":"se","negate":false},{"value":"presenten","negate":false},{"value":"a","negate":false},{"value":"las","negate":false},{"value":"próximas","negate":false},{"value":"elecciones","negate":false},{"value":"del","negate":false},{"value":"20","negate":false},{"value":"de","negate":false},{"value":"febrero","negate":false},{"value":"la","negate":false},{"value":"ola","negate":false},{"value":"de","negate":false},{"value":"dimisiones","negate":false},{"value":"sin","negate":false},{"value":"embargo","negate":false},{"value":"no","negate":true},{"value":"llega","negate":false},{"value":"hasta","negate":false},{"value":"el","negate":false},{"value":"presidente","negate":false},{"value":"mohamed","negate":false},{"value":"jatamí","negate":false},{"value":"quien","negate":false},{"value":"desmintió","negate":false},{"value":"los","negate":false},{"value":"rumores","negate":false},{"value":"de","negate":false},{"value":"su","negate":false},{"value":"presunto","negate":false},{"value":"abandono","negate":false},{"value":"del","negate":false},{"value":"cargo","negate":false},{"value":"e","negate":false},{"value":"incluso","negate":false},{"value":"auguró","negate":false},{"value":"una","negate":false},{"value":"próxima","negate":false},{"value":"solución","negate":false},{"value":"de","negate":false},{"value":"la","negate":false},{"value":"crisis","negate":false},{"value":"que","negate":false},{"value":"permitiría","negate":false},{"value":"la","negate":false},{"value":"celebración","negate":false},{"value":"de","negate":false},{"value":"elecciones","negate":false},{"value":"libres","negate":false},{"value":"tengo","negate":false},{"value":"la","negate":false},{"value":"intención","negate":false},{"value":"de","negate":false},{"value":"continuar","negate":false},{"value":"con","negate":false},{"value":"mi","negate":false},{"value":"labor","negate":false},{"value":"y","negate":false},{"value":"servicio","negate":false},{"value":"al","negate":false},{"value":"pueblo","negate":false},{"value":"declaró","negate":false},{"value":"en","negate":false},{"value":"suiza","negate":false},{"value":"donde","negate":false},{"value":"ha","negate":false},{"value":"mantenido","negate":false},{"value":"diversas","negate":false},{"value":"reuniones","negate":false},{"value":"con","negate":false},{"value":"autoridades","negate":false},{"value":"helvéticas","negate":false},{"value":"la","negate":false},{"value":"dimisión","negate":false},{"value":"colectiva","negate":false},{"value":"de","negate":false},{"value":"varios","negate":false},{"value":"ministros","negate":false},{"value":"fue","negate":false},{"value":"anunciada","negate":false},{"value":"por","negate":false},{"value":"el","negate":false},{"value":"vicepresidente","negate":false},{"value":"iraní","negate":false},{"value":"mohammed","negate":false},{"value":"alí","negate":false},{"value":"abtaji","negate":false},{"value":"quien","negate":false},{"value":"fue","negate":false},{"value":"también","negate":false},{"value":"quien","negate":false},{"value":"llegó","negate":false},{"value":"a","negate":false},{"value":"evocar","negate":false},{"value":"la","negate":false},{"value":"posibilidad","negate":false},{"value":"de","negate":false},{"value":"que","negate":false},{"value":"el","negate":false},{"value":"propio","negate":false},{"value":"jatamí","negate":false},{"value":"pudiese","negate":false},{"value":"presentar","negate":false},{"value":"su","negate":false},{"value":"renuncia","negate":false},{"value":"abtaji","negate":false},{"value":"recordó","negate":false},{"value":"las","negate":false},{"value":"antiguas","negate":false},{"value":"amenazas","negate":false},{"value":"de","negate":false},{"value":"jatamí","negate":false},{"value":"y","negate":false},{"value":"subvrayó","negate":false},{"value":"que","negate":false},{"value":"un","negate":false},{"value":"cierto","negate":false},{"value":"número","negate":false},{"value":"de","negate":false},{"value":"ministros","negate":false},{"value":"y","negate":false},{"value":"vicepresidentes","negate":false},{"value":"han","negate":false},{"value":"dimitido","negate":false},{"value":"pero","negate":false},{"value":"a","negate":false},{"value":"la","negate":false},{"value":"vez","negate":false},{"value":"dio","negate":false},{"value":"a","negate":false},{"value":"entender","negate":false},{"value":"que","negate":false},{"value":"la","negate":false},{"value":"presentación","negate":false},{"value":"de","negate":false},{"value":"la","negate":false},{"value":"dimisión","negate":false},{"value":"no","negate":true},{"value":"es","negate":false},{"value":"equivalente","negate":false},{"value":"a","negate":false},{"value":"su","negate":false},{"value":"renuncia","negate":false},{"value":"automática","negate":false},{"value":"explicó","negate":false},{"value":"a","negate":false},{"value":"este","negate":false},{"value":"respecto","negate":false},{"value":"que","negate":false},{"value":"antes","negate":false},{"value":"de","negate":false},{"value":"hacer","negate":false},{"value":"efectiva","negate":false},{"value":"su","negate":false},{"value":"salida","negate":false},{"value":"del","negate":false},{"value":"gobierno","negate":false},{"value":"los","negate":false},{"value":"dimisionarios","negate":false},{"value":"esperarán","negate":false},{"value":"el","negate":false},{"value":"resultado","negate":false},{"value":"de","negate":false},{"value":"las","negate":false},{"value":"deliberaciones","negate":false},{"value":"mantenidas","negate":false},{"value":"por","negate":false},{"value":"el","negate":false},{"value":"consejo","negate":false},{"value":"de","negate":false},{"value":"guardianes","negate":false},{"value":"de","negate":false},{"value":"la","negate":false},{"value":"constitución","negate":false},{"value":"núcleo","negate":false},{"value":"duro","negate":false},{"value":"de","negate":false},{"value":"los","negate":false},{"value":"inmovilistas","negate":false},{"value":"se","negate":false},{"value":"trata","negate":false},{"value":"por","negate":false},{"value":"tanto","negate":false},{"value":"de","negate":false},{"value":"unas","negate":false},{"value":"dimisiones","negate":false},{"value":"condicionadas","negate":false},{"value":"o","negate":false},{"value":"en","negate":false},{"value":"suspenso","negate":false},{"value":"pero","negate":false},{"value":"que","negate":false},{"value":"sirven","negate":false},{"value":"para","negate":false},{"value":"aumentar","negate":false},{"value":"la","negate":false},{"value":"presión","negate":false},{"value":"sobre","negate":false},{"value":"el","negate":false},{"value":"consejo","negate":false},{"value":"de","negate":false},{"value":"guardianes","negate":false},{"value":"en","negate":false},{"value":"el","negate":false},{"value":"pulso","negate":false},{"value":"que","negate":false},{"value":"ortodoxos","negate":false},{"value":"y","negate":false},{"value":"liberales","negate":false},{"value":"mantienen","negate":false},{"value":"ante","negate":false},{"value":"los","negate":false},{"value":"próximos","negate":false},{"value":"comicios","negate":false},{"value":"abtahi","negate":false},{"value":"reiteró","negate":false},{"value":"la","negate":false},{"value":"amenaza","negate":false},{"value":"lanzada","negate":false},{"value":"la","negate":false},{"value":"pasada","negate":false},{"value":"semana","negate":false},{"value":"por","negate":false},{"value":"jatamí","negate":false},{"value":"de","negate":false},{"value":"una","negate":false},{"value":"dimisión","negate":false},{"value":"en","negate":false},{"value":"bloque","negate":false},{"value":"de","negate":false},{"value":"todos","negate":false},{"value":"los","negate":false},{"value":"reformistas","negate":false},{"value":"que","negate":false},{"value":"controlan","negate":false},{"value":"la","negate":false},{"value":"presidencia","negate":false},{"value":"y","negate":false},{"value":"el","negate":false},{"value":"ejecutivo","negate":false},{"value":"iraní","negate":false},{"value":"si","negate":false},{"value":"el","negate":false},{"value":"consejo","negate":false},{"value":"de","negate":false},{"value":"guardianes","negate":false},{"value":"no","negate":true},{"value":"da","negate":false},{"value":"marcha","negate":false},{"value":"atrás","negate":false},{"value":"a","negate":false},{"value":"su","negate":false},{"value":"decisión","negate":false},{"value":"de","negate":false},{"value":"veto","negate":false},{"value":"colectivo","negate":false},{"value":"cuando","negate":false},{"value":"así","negate":false},{"value":"ocurra","negate":false},{"value":"aquí","negate":false},{"value":"todo","negate":false},{"value":"el","negate":false},{"value":"mundo","negate":false},{"value":"se","negate":false},{"value":"iría","negate":false},{"value":"afirmó","negate":false},{"value":"entonces","negate":false},{"value":"el","negate":false},{"value":"presidente","negate":false},{"value":"quien","negate":false},{"value":"sin","negate":false},{"value":"embargo","negate":false},{"value":"ayer","negate":false},{"value":"insistió","negate":false},{"value":"en","negate":false},{"value":"que","negate":false},{"value":"pese","negate":false},{"value":"a","negate":false},{"value":"todo","negate":false},{"value":"él","negate":false},{"value":"sigue","negate":false},{"value":"todavía","negate":false},{"value":"en","negate":false},{"value":"su","negate":false},{"value":"puesto","negate":false},{"value":"el","negate":false},{"value":"consejo","negate":false},{"value":"de","negate":false},{"value":"guardianes","negate":false},{"value":"ha","negate":false},{"value":"anulado","negate":false},{"value":"casi","negate":false},{"value":"la","negate":false},{"value":"mitad","negate":false},{"value":"de","negate":false},{"value":"las","negate":false},{"value":"candidaturas","negate":false},{"value":"electorales","negate":false},{"value":"en","negate":false},{"value":"una","negate":false},{"value":"decisión","negate":false},{"value":"que","negate":false},{"value":"los","negate":false},{"value":"reformistas","negate":false},{"value":"tildan","negate":false},{"value":"de","negate":false},{"value":"golpe","negate":false},{"value":"de","negate":false},{"value":"estado","negate":false},{"value":"el","negate":false},{"value":"científico","negate":false},{"value":"david","negate":false},{"value":"kelly","negate":false},{"value":"declaró","negate":false},{"value":"antes","negate":false},{"value":"de","negate":false},{"value":"suicidarse","negate":false},{"value":"que","negate":false},{"value":"irak","negate":false},{"value":"tenía","negate":false},{"value":"armas","negate":false},{"value":"de","negate":false},{"value":"destrucción","negate":false},{"value":"masiva","negate":false},{"value":"emili","negate":false},{"value":"j","negate":false},{"value":"blasco","negate":false},{"value":"corresponsal","negate":false},{"value":"londres","negate":false},{"value":"a","negate":false},{"value":"una","negate":false},{"value":"semana","negate":false},{"value":"de","negate":false},{"value":"la","negate":false},{"value":"publicación","negate":false},{"value":"del","negate":false},{"value":"informe","negate":false},{"value":"hutton","negate":false},{"value":"la","negate":false},{"value":"bbc","negate":false},{"value":"difundió","negate":false},{"value":"anoche","negate":false},{"value":"una","negate":false},{"value":"entrevista","negate":false},{"value":"nunca","negate":false},{"value":"emitida","negate":false},{"value":"en","negate":false},{"value":"la","negate":false},{"value":"que","negate":false},{"value":"el","negate":false},{"value":"experto","negate":false},{"value":"de","negate":false},{"value":"armas","negate":false},{"value":"david","negate":false},{"value":"kelly","negate":false},{"value":"aseguraba","negate":false},{"value":"que","negate":false},{"value":"irak","negate":false},{"value":"era","negate":false},{"value":"una","negate":false},{"value":"amenaza","negate":false},{"value":"inmediata","negate":false},{"value":"y","negate":false},{"value":"confirmaba","negate":false},{"value":"que","negate":false},{"value":"sadam","negate":false},{"value":"husein","negate":false},{"value":"tenía","negate":false},{"value":"armas","negate":false},{"value":"de","negate":false},{"value":"destrucción","negate":false},{"value":"masiva","negate":false},{"value":"el","negate":false},{"value":"suicidio","negate":false},{"value":"de","negate":false},{"value":"kelly","negate":false},{"value":"tras","negate":false},{"value":"la","negate":false},{"value":"acusación","negate":false},{"value":"lanzada","negate":false},{"value":"por","negate":false},{"value":"la","negate":false},{"value":"bbc","negate":false},{"value":"de","negate":false},{"value":"que","negate":false},{"value":"tony","negate":false},{"value":"blair","negate":false},{"value":"exageró","negate":false},{"value":"el","negate":false},{"value":"riesto","negate":false},{"value":"que","negate":false},{"value":"suponía","negate":false},{"value":"irak","negate":false},{"value":"abrieron","negate":false},{"value":"una","negate":false},{"value":"crisis","negate":false},{"value":"política","negate":false},{"value":"cuyas","negate":false},{"value":"dimensiones","negate":false},{"value":"debería","negate":false},{"value":"marcar","negate":false},{"value":"el","negate":false},{"value":"informe","negate":false},{"value":"del","negate":false},{"value":"juez","negate":false},{"value":"hutton","negate":false},{"value":"el","negate":false},{"value":"documental","negate":false},{"value":"de","negate":false},{"value":"panorama","negate":false},{"value":"emitido","negate":false},{"value":"anoche","negate":false},{"value":"pareció","negate":false},{"value":"reforzar","negate":false},{"value":"ciertos","negate":false},{"value":"aspectos","negate":false},{"value":"de","negate":false},{"value":"la","negate":false},{"value":"posición","negate":false},{"value":"del","negate":false},{"value":"gobierno","negate":false},{"value":"aunque","negate":false},{"value":"tampoco","negate":false},{"value":"le","negate":false},{"value":"dio","negate":false},{"value":"toda","negate":false},{"value":"la","negate":false},{"value":"razón","negate":false},{"value":"al","negate":false},{"value":"tiempo","negate":false},{"value":"que","negate":false},{"value":"censuraba","negate":false},{"value":"algunos","negate":false},{"value":"comportamientos","negate":false},{"value":"de","negate":false},{"value":"la","negate":false},{"value":"bbc","negate":false},{"value":"en","negate":false},{"value":"un","negate":false},{"value":"ejercicio","negate":false},{"value":"de","negate":false},{"value":"pluralidad","negate":false},{"value":"interna","negate":false},{"value":"difícilmente","negate":false},{"value":"imaginable","negate":false},{"value":"en","negate":false},{"value":"otras","negate":false},{"value":"radiotelevisiones","negate":false},{"value":"públicas","negate":false},{"value":"la","negate":false},{"value":"emisión","negate":false},{"value":"fue","negate":false},{"value":"elaborada","negate":false},{"value":"por","negate":false},{"value":"la","negate":false},{"value":"redacción","negate":false},{"value":"de","negate":false},{"value":"programas","negate":false},{"value":"informativos","negate":false},{"value":"de","negate":false},{"value":"la","negate":false},{"value":"bbc","negate":false},{"value":"en","negate":false},{"value":"lo","negate":false},{"value":"que","negate":false},{"value":"algunos","negate":false},{"value":"comentaristas","negate":false},{"value":"han","negate":false},{"value":"visto","negate":false},{"value":"una","negate":false},{"value":"batalla","negate":false},{"value":"interna","negate":false},{"value":"con-","negate":false},{"value":"tra","negate":false},{"value":"la","negate":false},{"value":"redacción","negate":false},{"value":"de","negate":false},{"value":"informativos","negate":false},{"value":"diarios","negate":false},{"value":"de","negate":false},{"value":"la","negate":false},{"value":"que","negate":false},{"value":"formaba","negate":false},{"value":"parte","negate":false},{"value":"el","negate":false},{"value":"programa","negate":false},{"value":"today","negate":false},{"value":"de","negate":false},{"value":"andrew","negate":false},{"value":"gilligan","negate":false},{"value":"desencadenante","negate":false},{"value":"de","negate":false},{"value":"la","negate":false},{"value":"polémica","negate":false},{"value":"la","negate":false},{"value":"entrevista","negate":false},{"value":"con","negate":false},{"value":"kelly","negate":false},{"value":"fue","negate":false},{"value":"realizada","negate":false},{"value":"en","negate":false},{"value":"octubre","negate":false},{"value":"de","negate":false},{"value":"2002","negate":false},{"value":"un","negate":false},{"value":"mes","negate":false},{"value":"después","negate":false},{"value":"de","negate":false},{"value":"que","negate":false},{"value":"blair","negate":false},{"value":"presentara","negate":false},{"value":"el","negate":false},{"value":"polémico","negate":false},{"value":"informe","negate":false},{"value":"en","negate":false},{"value":"el","negate":false},{"value":"que","negate":false},{"value":"se","negate":false},{"value":"aseguraba","negate":false},{"value":"que","negate":false},{"value":"irak","negate":false},{"value":"suponía","negate":false},{"value":"un","negate":false},{"value":"riesgo","negate":false},{"value":"para","negate":false},{"value":"la","negate":false},{"value":"paz","negate":false},{"value":"y","negate":false},{"value":"podía","negate":false},{"value":"emplear","negate":false},{"value":"sus","negate":false},{"value":"armas","negate":false},{"value":"de","negate":false},{"value":"destrucción","negate":false},{"value":"masiva","negate":false},{"value":"en","negate":false},{"value":"apenas","negate":false},{"value":"45","negate":false},{"value":"minutos","negate":false},{"value":"en","negate":false},{"value":"esa","negate":false},{"value":"entrevista","negate":false},{"value":"cuya","negate":false},{"value":"no","negate":true},{"value":"difusión","negate":false},{"value":"en","negate":false},{"value":"todo","negate":false},{"value":"este","negate":false},{"value":"tiempo","negate":false},{"value":"no","negate":true},{"value":"ha","negate":false},{"value":"sido","negate":false},{"value":"justificada","negate":false},{"value":"por","negate":false},{"value":"la","negate":false},{"value":"dirección","negate":false},{"value":"de","negate":false},{"value":"la","negate":false},{"value":"bbc","negate":false},{"value":"kelly","negate":false},{"value":"daba","negate":false},{"value":"la","negate":false},{"value":"razón","negate":false},{"value":"al","negate":false},{"value":"gobierno","negate":false},{"value":"en","negate":false},{"value":"el","negate":false},{"value":"sentido","negate":false},{"value":"de","negate":false},{"value":"que","negate":false},{"value":"sadam","negate":false},{"value":"era","negate":false},{"value":"una","negate":false},{"value":"amenaza","negate":false},{"value":"inmediata","negate":false},{"value":"pero","negate":false},{"value":"venía","negate":false},{"value":"a","negate":false},{"value":"negar","negate":false},{"value":"que","negate":false},{"value":"estuviera","negate":false},{"value":"en","negate":false},{"value":"disposición","negate":false},{"value":"de","negate":false},{"value":"sus","negate":false},{"value":"armas","negate":false},{"value":"de","negate":false},{"value":"destrucción","negate":false},{"value":"masiva","negate":false},{"value":"en","negate":false},{"value":"45","negate":false},{"value":"minutos","negate":false},{"value":"ya","negate":false},{"value":"que","negate":false},{"value":"en","negate":false},{"value":"su","negate":false},{"value":"opinión","negate":false},{"value":"éstas","negate":false},{"value":"sólo","negate":false},{"value":"podían","negate":false},{"value":"estar","negate":false},{"value":"operativas","negate":false},{"value":"en","negate":false},{"value":"cuestión","negate":false},{"value":"de","negate":false},{"value":"días","negate":false},{"value":"o","negate":false},{"value":"semanas","negate":false},{"value":"el","negate":false},{"value":"programa","negate":false},{"value":"llegó","negate":false},{"value":"a","negate":false},{"value":"afirmar","negate":false},{"value":"que","negate":false},{"value":"gilligan","negate":false},{"value":"estaba","negate":false},{"value":"equivocado","negate":false},{"value":"cuando","negate":false},{"value":"dijo","negate":false},{"value":"que","negate":false},{"value":"downing","negate":false},{"value":"street","negate":false},{"value":"ordenó","negate":false},{"value":"a","negate":false},{"value":"los","negate":false},{"value":"servicios","negate":false},{"value":"de","negate":false},{"value":"inteligencia","negate":false},{"value":"que","negate":false},{"value":"exagerasen","negate":false},{"value":"los","negate":false},{"value":"datos","negate":false},{"value":"descargar","negate":false},{"value":"esta","negate":false},{"value":"página","negate":false},{"value":"en","negate":false},{"value":"pdfañadir","negate":false},{"value":"a","negate":false},{"value":"mi","negate":false},{"value":"dossierquitar","negate":false},{"value":"de","negate":false},{"value":"mi","negate":false},{"value":"dossierinit","negate":false},{"value":"'0004869076'","negate":false},{"value":"enviar","negate":false},{"value":"a","negate":false},{"value":"un","negate":false},{"value":"amigoenlazare-mail","negate":false},{"value":"del","negate":false},{"value":"remitentee-mail","negate":false},{"value":"del","negate":false},{"value":"destinatariocomentariourl","negate":false},{"value":"directa","negate":false},{"value":"a","negate":false},{"value":"la","negate":false},{"value":"página","negate":false},{"value":"insertar","negate":false},{"value":"en","negate":false},{"value":"un","negate":false},{"value":"blog","negate":false},{"value":"url","negate":false},{"value":"directa","negate":false},{"value":"a","negate":false},{"value":"la","negate":false},{"value":"página","negate":false},{"value":"abc","negate":false},{"value":"jueves","negate":false},{"value":"22","negate":false},{"value":"1","negate":false},{"value":"2004","negate":false},{"value":"internacional","negate":false},{"value":"29","negate":false},{"value":"varios","negate":false},{"value":"ministros","negate":false},{"value":"iraníes","negate":false},{"value":"presentan","negate":false},{"value":"su","negate":false},{"value":"dimisión","negate":false},{"value":"para","negate":false},{"value":"presionar","negate":false},{"value":"a","negate":false},{"value":"los","negate":false},{"value":"inmovilistas","negate":false},{"value":"jatamí","negate":false},{"value":"subraya","negate":false},{"value":"desde","negate":false},{"value":"suiza","negate":false},{"value":"que","negate":false},{"value":"por","negate":false},{"value":"ahora","negate":false},{"value":"no","negate":true},{"value":"tiene","negate":false},{"value":"la","negate":false},{"value":"intención","negate":false},{"value":"de","negate":false},{"value":"abandonar","negate":false},{"value":"su","negate":false},{"value":"puesto","negate":false},{"value":"b","negate":false},{"value":"la","negate":false},{"value":"dimisión","negate":false},{"value":"presentada","negate":false},{"value":"ayer","negate":false},{"value":"por","negate":false},{"value":"varios","negate":false},{"value":"ministros","negate":false},{"value":"no","negate":true},{"value":"es","negate":false},{"value":"equivalente","negate":false},{"value":"a","negate":false},{"value":"su","negate":false},{"value":"renuncia","negate":false},{"value":"automática","negate":false},{"value":"ya","negate":false},{"value":"que","negate":false},{"value":"los","negate":false},{"value":"dimisionarios","negate":false},{"value":"aún","negate":false},{"value":"esperan","negate":false},{"value":"que","negate":false},{"value":"los","negate":false},{"value":"conservadores","negate":false},{"value":"rectifiquen","negate":false},{"value":"abc","negate":false},{"value":"teherán","negate":false},{"value":"los","negate":false},{"value":"reformistas","negate":false},{"value":"iraníes","negate":false},{"value":"han","negate":false},{"value":"aumentado","negate":false},{"value":"la","negate":false},{"value":"presión","negate":false},{"value":"sobre","negate":false},{"value":"sus","negate":false},{"value":"adversarios","negate":false},{"value":"inmovilistas","negate":false},{"value":"después","negate":false},{"value":"de","negate":false},{"value":"que","negate":false},{"value":"varios","negate":false},{"value":"ministros","negate":false},{"value":"presentasen","negate":false},{"value":"ayer","negate":false},{"value":"su","negate":false},{"value":"dimisión","negate":false},{"value":"para","negate":false},{"value":"protestar","negate":false},{"value":"por","negate":false},{"value":"la","negate":false},{"value":"decisión","negate":false},{"value":"de","negate":false},{"value":"impedir","negate":false},{"value":"que","negate":false},{"value":"un","negate":false},{"value":"alto","negate":false},{"value":"número","negate":false},{"value":"de","negate":false},{"value":"candidatos","negate":false},{"value":"liberales","negate":false},{"value":"se","negate":false},{"value":"presenten","negate":false},{"value":"a","negate":false},{"value":"las","negate":false},{"value":"próximas","negate":false},{"value":"elecciones","negate":false},{"value":"del","negate":false},{"value":"20","negate":false},{"value":"de","negate":false},{"value":"febrero","negate":false},{"value":"la","negate":false},{"value":"ola","negate":false},{"value":"de","negate":false},{"value":"dimisiones","negate":false},{"value":"sin","negate":false},{"value":"embargo","negate":false},{"value":"no","negate":true},{"value":"llega","negate":false},{"value":"hasta","negate":false},{"value":"el","negate":false},{"value":"presidente","negate":false},{"value":"mohamed","negate":false},{"value":"jatamí","negate":false},{"value":"quien","negate":false},{"value":"desmintió","negate":false},{"value":"los","negate":false},{"value":"rumores","negate":false},{"value":"de","negate":false},{"value":"su","negate":false},{"value":"presunto","negate":false},{"value":"abandono","negate":false},{"value":"del","negate":false},{"value":"cargo","negate":false},{"value":"e","negate":false},{"value":"incluso","negate":false},{"value":"auguró","negate":false},{"value":"una","negate":false},{"value":"próxima","negate":false},{"value":"solución","negate":false},{"value":"de","negate":false},{"value":"la","negate":false},{"value":"crisis","negate":false},{"value":"que","negate":false},{"value":"permitiría","negate":false},{"value":"la","negate":false},{"value":"celebración","negate":false},{"value":"de","negate":false},{"value":"elecciones","negate":false},{"value":"libres","negate":false},{"value":"tengo","negate":false},{"value":"la","negate":false},{"value":"intención","negate":false},{"value":"de","negate":false},{"value":"continuar","negate":false},{"value":"con","negate":false},{"value":"mi","negate":false},{"value":"labor","negate":false},{"value":"y","negate":false},{"value":"servicio","negate":false},{"value":"al","negate":false},{"value":"pueblo","negate":false},{"value":"declaró","negate":false},{"value":"en","negate":false},{"value":"suiza","negate":false},{"value":"donde","negate":false},{"value":"ha","negate":false},{"value":"mantenido","negate":false},{"value":"diversas","negate":false},{"value":"reuniones","negate":false},{"value":"con","negate":false},{"value":"autoridades","negate":false},{"value":"helvéticas","negate":false},{"value":"la","negate":false},{"value":"dimisión","negate":false},{"value":"colectiva","negate":false},{"value":"de","negate":false},{"value":"varios","negate":false},{"value":"ministros","negate":false},{"value":"fue","negate":false},{"value":"anunciada","negate":false},{"value":"por","negate":false},{"value":"el","negate":false},{"value":"vicepresidente","negate":false},{"value":"iraní","negate":false},{"value":"mohammed","negate":false},{"value":"alí","negate":false},{"value":"abtaji","negate":false},{"value":"quien","negate":false},{"value":"fue","negate":false},{"value":"también","negate":false},{"value":"quien","negate":false},{"value":"llegó","negate":false},{"value":"a","negate":false},{"value":"evocar","negate":false},{"value":"la","negate":false},{"value":"posibilidad","negate":false},{"value":"de","negate":false},{"value":"que","negate":false},{"value":"el","negate":false},{"value":"propio","negate":false},{"value":"jatamí","negate":false},{"value":"pudiese","negate":false},{"value":"presentar","negate":false},{"value":"su","negate":false},{"value":"renuncia","negate":false},{"value":"abtaji","negate":false},{"value":"recordó","negate":false},{"value":"las","negate":false},{"value":"antiguas","negate":false},{"value":"amenazas","negate":false},{"value":"de","negate":false},{"value":"jatamí","negate":false},{"value":"y","negate":false},{"value":"subvrayó","negate":false},{"value":"que","negate":false},{"value":"un","negate":false},{"value":"cierto","negate":false},{"value":"número","negate":false},{"value":"de","negate":false},{"value":"ministros","negate":false},{"value":"y","negate":false},{"value":"vicepresidentes","negate":false},{"value":"han","negate":false},{"value":"dimitido","negate":false},{"value":"pero","negate":false},{"value":"a","negate":false},{"value":"la","negate":false},{"value":"vez","negate":false},{"value":"dio","negate":false},{"value":"a","negate":false},{"value":"entender","negate":false},{"value":"que","negate":false},{"value":"la","negate":false},{"value":"presentación","negate":false},{"value":"de","negate":false},{"value":"la","negate":false},{"value":"dimisión","negate":false},{"value":"no","negate":true},{"value":"es","negate":false},{"value":"equivalente","negate":false},{"value":"a","negate":false},{"value":"su","negate":false},{"value":"renuncia","negate":false},{"value":"automática","negate":false},{"value":"explicó","negate":false},{"value":"a","negate":false},{"value":"este","negate":false},{"value":"respecto","negate":false},{"value":"que","negate":false},{"value":"antes","negate":false},{"value":"de","negate":false},{"value":"hacer","negate":false},{"value":"efectiva","negate":false},{"value":"su","negate":false},{"value":"salida","negate":false},{"value":"del","negate":false},{"value":"gobierno","negate":false},{"value":"los","negate":false},{"value":"dimisionarios","negate":false},{"value":"esperarán","negate":false},{"value":"el","negate":false},{"value":"resultado","negate":false},{"value":"de","negate":false},{"value":"las","negate":false},{"value":"deliberaciones","negate":false},{"value":"mantenidas","negate":false},{"value":"por","negate":false},{"value":"el","negate":false},{"value":"consejo","negate":false},{"value":"de","negate":false},{"value":"guardianes","negate":false},{"value":"de","negate":false},{"value":"la","negate":false},{"value":"constitución","negate":false},{"value":"núcleo","negate":false},{"value":"duro","negate":false},{"value":"de","negate":false},{"value":"los","negate":false},{"value":"inmovilistas","negate":false},{"value":"se","negate":false},{"value":"trata","negate":false},{"value":"por","negate":false},{"value":"tanto","negate":false},{"value":"de","negate":false},{"value":"unas","negate":false},{"value":"dimisiones","negate":false},{"value":"condicionadas","negate":false},{"value":"o","negate":false},{"value":"en","negate":false},{"value":"suspenso","negate":false},{"value":"pero","negate":false},{"value":"que","negate":false},{"value":"sirven","negate":false},{"value":"para","negate":false},{"value":"aumentar","negate":false},{"value":"la","negate":false},{"value":"presión","negate":false},{"value":"sobre","negate":false},{"value":"el","negate":false},{"value":"consejo","negate":false},{"value":"de","negate":false},{"value":"guardianes","negate":false},{"value":"en","negate":false},{"value":"el","negate":false},{"value":"pulso","negate":false},{"value":"que","negate":false},{"value":"ortodoxos","negate":false},{"value":"y","negate":false},{"value":"liberales","negate":false},{"value":"mantienen","negate":false},{"value":"ante","negate":false},{"value":"los","negate":false},{"value":"próximos","negate":false},{"value":"comicios","negate":false},{"value":"abtahi","negate":false},{"value":"reiteró","negate":false},{"value":"la","negate":false},{"value":"amenaza","negate":false},{"value":"lanzada","negate":false},{"value":"la","negate":false},{"value":"pasada","negate":false},{"value":"semana","negate":false},{"value":"por","negate":false},{"value":"jatamí","negate":false},{"value":"de","negate":false},{"value":"una","negate":false},{"value":"dimisión","negate":false},{"value":"en","negate":false},{"value":"bloque","negate":false},{"value":"de","negate":false},{"value":"todos","negate":false},{"value":"los","negate":false},{"value":"reformistas","negate":false},{"value":"que","negate":false},{"value":"controlan","negate":false},{"value":"la","negate":false},{"value":"presidencia","negate":false},{"value":"y","negate":false},{"value":"el","negate":false},{"value":"ejecutivo","negate":false},{"value":"iraní","negate":false},{"value":"si","negate":false},{"value":"el","negate":false},{"value":"consejo","negate":false},{"value":"de","negate":false},{"value":"guardianes","negate":false},{"value":"no","negate":true},{"value":"da","negate":false},{"value":"marcha","negate":false},{"value":"atrás","negate":false},{"value":"a","negate":false},{"value":"su","negate":false},{"value":"decisión","negate":false},{"value":"de","negate":false},{"value":"veto","negate":false},{"value":"colectivo","negate":false},{"value":"cuando","negate":false},{"value":"así","negate":false},{"value":"ocurra","negate":false},{"value":"aquí","negate":false},{"value":"todo","negate":false},{"value":"el","negate":false},{"value":"mundo","negate":false},{"value":"se","negate":false},{"value":"iría","negate":false},{"value":"afirmó","negate":false},{"value":"entonces","negate":false},{"value":"el","negate":false},{"value":"presidente","negate":false},{"value":"quien","negate":false},{"value":"sin","negate":false},{"value":"embargo","negate":false},{"value":"ayer","negate":false},{"value":"insistió","negate":false},{"value":"en","negate":false},{"value":"que","negate":false},{"value":"pese","negate":false},{"value":"a","negate":false},{"value":"todo","negate":false},{"value":"él","negate":false},{"value":"sigue","negate":false},{"value":"todavía","negate":false},{"value":"en","negate":false},{"value":"su","negate":false},{"value":"puesto","negate":false},{"value":"el","negate":false},{"value":"consejo","negate":false},{"value":"de","negate":false},{"value":"guardianes","negate":false},{"value":"ha","negate":false},{"value":"anulado","negate":false},{"value":"casi","negate":false},{"value":"la","negate":false},{"value":"mitad","negate":false},{"value":"de","negate":false},{"value":"las","negate":false},{"value":"candidaturas","negate":false},{"value":"electorales","negate":false},{"value":"en","negate":false},{"value":"una","negate":false},{"value":"decisión","negate":false},{"value":"que","negate":false},{"value":"los","negate":false},{"value":"reformistas","negate":false},{"value":"tildan","negate":false},{"value":"de","negate":false},{"value":"golpe","negate":false},{"value":"de","negate":false},{"value":"estado","negate":false},{"value":"el","negate":false},{"value":"científico","negate":false},{"value":"david","negate":false},{"value":"kelly","negate":false},{"value":"declaró","negate":false},{"value":"antes","negate":false},{"value":"de","negate":false},{"value":"suicidarse","negate":false},{"value":"que","negate":false},{"value":"irak","negate":false},{"value":"tenía","negate":false},{"value":"armas","negate":false},{"value":"de","negate":false},{"value":"destrucción","negate":false},{"value":"masiva","negate":false},{"value":"emili","negate":false},{"value":"j","negate":false},{"value":"blasco","negate":false},{"value":"corresponsal","negate":false},{"value":"londres","negate":false},{"value":"a","negate":false},{"value":"una","negate":false},{"value":"semana","negate":false},{"value":"de","negate":false},{"value":"la","negate":false},{"value":"publicación","negate":false},{"value":"del","negate":false},{"value":"informe","negate":false},{"value":"hutton","negate":false},{"value":"la","negate":false},{"value":"bbc","negate":false},{"value":"difundió","negate":false},{"value":"anoche","negate":false},{"value":"una","negate":false},{"value":"entrevista","negate":false},{"value":"nunca","negate":false},{"value":"emitida","negate":false},{"value":"en","negate":false},{"value":"la","negate":false},{"value":"que","negate":false},{"value":"el","negate":false},{"value":"experto","negate":false},{"value":"de","negate":false},{"value":"armas","negate":false},{"value":"david","negate":false},{"value":"kelly","negate":false},{"value":"aseguraba","negate":false},{"value":"que","negate":false},{"value":"irak","negate":false},{"value":"era","negate":false},{"value":"una","negate":false},{"value":"amenaza","negate":false},{"value":"inmediata","negate":false},{"value":"y","negate":false},{"value":"confirmaba","negate":false},{"value":"que","negate":false},{"value":"sadam","negate":false},{"value":"husein","negate":false},{"value":"tenía","negate":false},{"value":"armas","negate":false},{"value":"de","negate":false},{"value":"destrucción","negate":false},{"value":"masiva","negate":false},{"value":"el","negate":false},{"value":"suicidio","negate":false},{"value":"de","negate":false},{"value":"kelly","negate":false},{"value":"tras","negate":false},{"value":"la","negate":false},{"value":"acusación","negate":false},{"value":"lanzada","negate":false},{"value":"por","negate":false},{"value":"la","negate":false},{"value":"bbc","negate":false},{"value":"de","negate":false},{"value":"que","negate":false},{"value":"tony","negate":false},{"value":"blair","negate":false},{"value":"exageró","negate":false},{"value":"el","negate":false},{"value":"riesto","negate":false},{"value":"que","negate":false},{"value":"suponía","negate":false},{"value":"irak","negate":false},{"value":"abrieron","negate":false},{"value":"una","negate":false},{"value":"crisis","negate":false},{"value":"política","negate":false},{"value":"cuyas","negate":false},{"value":"dimensiones","negate":false},{"value":"debería","negate":false},{"value":"marcar","negate":false},{"value":"el","negate":false},{"value":"informe","negate":false},{"value":"del","negate":false},{"value":"juez","negate":false},{"value":"hutton","negate":false},{"value":"el","negate":false},{"value":"documental","negate":false},{"value":"de","negate":false},{"value":"panorama","negate":false},{"value":"emitido","negate":false},{"value":"anoche","negate":false},{"value":"pareció","negate":false},{"value":"reforzar","negate":false},{"value":"ciertos","negate":false},{"value":"aspectos","negate":false},{"value":"de","negate":false},{"value":"la","negate":false},{"value":"posición","negate":false},{"value":"del","negate":false},{"value":"gobierno","negate":false},{"value":"aunque","negate":false},{"value":"tampoco","negate":false},{"value":"le","negate":false},{"value":"dio","negate":false},{"value":"toda","negate":false},{"value":"la","negate":false},{"value":"razón","negate":false},{"value":"al","negate":false},{"value":"tiempo","negate":false},{"value":"que","negate":false},{"value":"censuraba","negate":false},{"value":"algunos","negate":false},{"value":"comportamientos","negate":false},{"value":"de","negate":false},{"value":"la","negate":false},{"value":"bbc","negate":false},{"value":"en","negate":false},{"value":"un","negate":false},{"value":"ejercicio","negate":false},{"value":"de","negate":false},{"value":"pluralidad","negate":false},{"value":"interna","negate":false},{"value":"difícilmente","negate":false},{"value":"imaginable","negate":false},{"value":"en","negate":false},{"value":"otras","negate":false},{"value":"radiotelevisiones","negate":false},{"value":"públicas","negate":false},{"value":"la","negate":false},{"value":"emisión","negate":false},{"value":"fue","negate":false},{"value":"elaborada","negate":false},{"value":"por","negate":false},{"value":"la","negate":false},{"value":"redacción","negate":false},{"value":"de","negate":false},{"value":"programas","negate":false},{"value":"informativos","negate":false},{"value":"de","negate":false},{"value":"la","negate":false},{"value":"bbc","negate":false},{"value":"en","negate":false},{"value":"lo","negate":false},{"value":"que","negate":false},{"value":"algunos","negate":false},{"value":"comentaristas","negate":false},{"value":"han","negate":false},{"value":"visto","negate":false},{"value":"una","negate":false},{"value":"batalla","negate":false},{"value":"interna","negate":false},{"value":"con-","negate":false},{"value":"tra","negate":false},{"value":"la","negate":false},{"value":"redacción","negate":false},{"value":"de","negate":false},{"value":"informativos","negate":false},{"value":"diarios","negate":false},{"value":"de","negate":false},{"value":"la","negate":false},{"value":"que","negate":false},{"value":"formaba","negate":false},{"value":"parte","negate":false},{"value":"el","negate":false},{"value":"programa","negate":false},{"value":"today","negate":false},{"value":"de","negate":false},{"value":"andrew","negate":false},{"value":"gilligan","negate":false},{"value":"desencadenante","negate":false},{"value":"de","negate":false},{"value":"la","negate":false},{"value":"polémica","negate":false},{"value":"la","negate":false},{"value":"entrevista","negate":false},{"value":"con","negate":false},{"value":"kelly","negate":false},{"value":"fue","negate":false},{"value":"realizada","negate":false},{"value":"en","negate":false},{"value":"octubre","negate":false},{"value":"de","negate":false},{"value":"2002","negate":false},{"value":"un","negate":false},{"value":"mes","negate":false},{"value":"después","negate":false},{"value":"de","negate":false},{"value":"que","negate":false},{"value":"blair","negate":false},{"value":"presentara","negate":false},{"value":"el","negate":false},{"value":"polémico","negate":false},{"value":"informe","negate":false},{"value":"en","negate":false},{"value":"el","negate":false},{"value":"que","negate":false},{"value":"se","negate":false},{"value":"aseguraba","negate":false},{"value":"que","negate":false},{"value":"irak","negate":false},{"value":"suponía","negate":false},{"value":"un","negate":false},{"value":"riesgo","negate":false},{"value":"para","negate":false},{"value":"la","negate":false},{"value":"paz","negate":false},{"value":"y","negate":false},{"value":"podía","negate":false},{"value":"emplear","negate":false},{"value":"sus","negate":false},{"value":"armas","negate":false},{"value":"de","negate":false},{"value":"destrucción","negate":false},{"value":"masiva","negate":false},{"value":"en","negate":false},{"value":"apenas","negate":false},{"value":"45","negate":false},{"value":"minutos","negate":false},{"value":"en","negate":false},{"value":"esa","negate":false},{"value":"entrevista","negate":false},{"value":"cuya","negate":false},{"value":"no","negate":true},{"value":"difusión","negate":false},{"value":"en","negate":false},{"value":"todo","negate":false},{"value":"este","negate":false},{"value":"tiempo","negate":false},{"value":"no","negate":true},{"value":"ha","negate":false},{"value":"sido","negate":false},{"value":"justificada","negate":false},{"value":"por","negate":false},{"value":"la","negate":false},{"value":"dirección","negate":false},{"value":"de","negate":false},{"value":"la","negate":false},{"value":"bbc","negate":false},{"value":"kelly","negate":false},{"value":"daba","negate":false},{"value":"la","negate":false},{"value":"razón","negate":false},{"value":"al","negate":false},{"value":"gobierno","negate":false},{"value":"en","negate":false},{"value":"el","negate":false},{"value":"sentido","negate":false},{"value":"de","negate":false},{"value":"que","negate":false},{"value":"sadam","negate":false},{"value":"era","negate":false},{"value":"una","negate":false},{"value":"amenaza","negate":false},{"value":"inmediata","negate":false},{"value":"pero","negate":false},{"value":"venía","negate":false},{"value":"a","negate":false},{"value":"negar","negate":false},{"value":"que","negate":false},{"value":"estuviera","negate":false},{"value":"en","negate":false},{"value":"disposición","negate":false},{"value":"de","negate":false},{"value":"sus","negate":false},{"value":"armas","negate":false},{"value":"de","negate":false},{"value":"destrucción","negate":false},{"value":"masiva","negate":false},{"value":"en","negate":false},{"value":"45","negate":false},{"value":"minutos","negate":false},{"value":"ya","negate":false},{"value":"que","negate":false},{"value":"en","negate":false},{"value":"su","negate":false},{"value":"opinión","negate":false},{"value":"éstas","negate":false},{"value":"sólo","negate":false},{"value":"podían","negate":false},{"value":"estar","negate":false},{"value":"operativas","negate":false},{"value":"en","negate":false},{"value":"cuestión","negate":false},{"value":"de","negate":false},{"value":"días","negate":false},{"value":"o","negate":false},{"value":"semanas","negate":false},{"value":"el","negate":false},{"value":"programa","negate":false},{"value":"llegó","negate":false},{"value":"a","negate":false},{"value":"afirmar","negate":false},{"value":"que","negate":false},{"value":"gilligan","negate":false},{"value":"estaba","negate":false},{"value":"equivocado","negate":false},{"value":"cuando","negate":false},{"value":"dijo","negate":false},{"value":"que","negate":false},{"value":"downing","negate":false},{"value":"street","negate":false},{"value":"ordenó","negate":false},{"value":"a","negate":false},{"value":"los","negate":false},{"value":"servicios","negate":false},{"value":"de","negate":false},{"value":"inteligencia","negate":false},{"value":"que","negate":false},{"value":"exagerasen","negate":false},{"value":"los","negate":false},{"value":"datos","negate":false},{"value":"abc","negate":false},{"value":"jueves","negate":false},{"value":"22","negate":false},{"value":"1","negate":false},{"value":"2004","negate":false},{"value":"internacional","negate":false},{"value":"29","negate":false},{"value":"varios","negate":false},{"value":"ministros","negate":false},{"value":"iraníes","negate":false},{"value":"presentan","negate":false},{"value":"su","negate":false},{"value":"dimisión","negate":false},{"value":"para","negate":false},{"value":"presionar","negate":false},{"value":"a","negate":false},{"value":"los","negate":false},{"value":"inmovilistas","negate":false},{"value":"jatamí","negate":false},{"value":"subraya","negate":false},{"value":"desde","negate":false},{"value":"suiza","negate":false},{"value":"que","negate":false},{"value":"por","negate":false},{"value":"ahora","negate":false},{"value":"no","negate":true},{"value":"tiene","negate":false},{"value":"la","negate":false},{"value":"intención","negate":false},{"value":"de","negate":false},{"value":"abandonar","negate":false},{"value":"su","negate":false},{"value":"puesto","negate":false},{"value":"b","negate":false},{"value":"la","negate":false},{"value":"dimisión","negate":false},{"value":"presentada","negate":false},{"value":"ayer","negate":false},{"value":"por","negate":false},{"value":"varios","negate":false},{"value":"ministros","negate":false},{"value":"no","negate":true},{"value":"es","negate":false},{"value":"equivalente","negate":false},{"value":"a","negate":false},{"value":"su","negate":false},{"value":"renuncia","negate":false},{"value":"automática","negate":false},{"value":"ya","negate":false},{"value":"que","negate":false},{"value":"los","negate":false},{"value":"dimisionarios","negate":false},{"value":"aún","negate":false},{"value":"esperan","negate":false},{"value":"que","negate":false},{"value":"los","negate":false},{"value":"conservadores","negate":false},{"value":"rectifiquen","negate":false},{"value":"abc","negate":false},{"value":"teherán","negate":false},{"value":"los","negate":false},{"value":"reformistas","negate":false},{"value":"iraníes","negate":false},{"value":"han","negate":false},{"value":"aumentado","negate":false},{"value":"la","negate":false},{"value":"presión","negate":false},{"value":"sobre","negate":false},{"value":"sus","negate":false},{"value":"adversarios","negate":false},{"value":"inmovilistas","negate":false},{"value":"después","negate":false},{"value":"de","negate":false},{"value":"que","negate":false},{"value":"varios","negate":false},{"value":"ministros","negate":false},{"value":"presentasen","negate":false},{"value":"ayer","negate":false},{"value":"su","negate":false},{"value":"dimisión","negate":false},{"value":"para","negate":false},{"value":"protestar","negate":false},{"value":"por","negate":false},{"value":"la","negate":false},{"value":"decisión","negate":false},{"value":"de","negate":false},{"value":"impedir","negate":false},{"value":"que","negate":false},{"value":"un","negate":false},{"value":"alto","negate":false},{"value":"número","negate":false},{"value":"de","negate":false},{"value":"candidatos","negate":false},{"value":"liberales","negate":false},{"value":"se","negate":false},{"value":"presenten","negate":false},{"value":"a","negate":false},{"value":"las","negate":false},{"value":"próximas","negate":false},{"value":"elecciones","negate":false},{"value":"del","negate":false},{"value":"20","negate":false},{"value":"de","negate":false},{"value":"febrero","negate":false},{"value":"la","negate":false},{"value":"ola","negate":false},{"value":"de","negate":false},{"value":"dimisiones","negate":false},{"value":"sin","negate":false},{"value":"embargo","negate":false},{"value":"no","negate":true},{"value":"llega","negate":false},{"value":"hasta","negate":false},{"value":"el","negate":false},{"value":"presidente","negate":false},{"value":"mohamed","negate":false},{"value":"jatamí","negate":false},{"value":"quien","negate":false},{"value":"desmintió","negate":false},{"value":"los","negate":false},{"value":"rumores","negate":false},{"value":"de","negate":false},{"value":"su","negate":false},{"value":"presunto","negate":false},{"value":"abandono","negate":false},{"value":"del","negate":false},{"value":"cargo","negate":false},{"value":"e","negate":false},{"value":"incluso","negate":false},{"value":"auguró","negate":false},{"value":"una","negate":false},{"value":"próxima","negate":false},{"value":"solución","negate":false},{"value":"de","negate":false},{"value":"la","negate":false},{"value":"crisis","negate":false},{"value":"que","negate":false},{"value":"permitiría","negate":false},{"value":"la","negate":false},{"value":"celebración","negate":false},{"value":"de","negate":false},{"value":"elecciones","negate":false},{"value":"libres","negate":false},{"value":"tengo","negate":false},{"value":"la","negate":false},{"value":"intención","negate":false},{"value":"de","negate":false},{"value":"continuar","negate":false},{"value":"con","negate":false},{"value":"mi","negate":false},{"value":"labor","negate":false},{"value":"y","negate":false},{"value":"servicio","negate":false},{"value":"al","negate":false},{"value":"pueblo","negate":false},{"value":"declaró","negate":false},{"value":"en","negate":false},{"value":"suiza","negate":false},{"value":"donde","negate":false},{"value":"ha","negate":false},{"value":"mantenido","negate":false},{"value":"diversas","negate":false},{"value":"reuniones","negate":false},{"value":"con","negate":false},{"value":"autoridades","negate":false},{"value":"helvéticas","negate":false},{"value":"la","negate":false},{"value":"dimisión","negate":false},{"value":"colectiva","negate":false},{"value":"de","negate":false},{"value":"varios","negate":false},{"value":"ministros","negate":false},{"value":"fue","negate":false},{"value":"anunciada","negate":false},{"value":"por","negate":false},{"value":"el","negate":false},{"value":"vicepresidente","negate":false},{"value":"iraní","negate":false},{"value":"mohammed","negate":false},{"value":"alí","negate":false},{"value":"abtaji","negate":false},{"value":"quien","negate":false},{"value":"fue","negate":false},{"value":"también","negate":false},{"value":"quien","negate":false},{"value":"llegó","negate":false},{"value":"a","negate":false},{"value":"evocar","negate":false},{"value":"la","negate":false},{"value":"posibilidad","negate":false},{"value":"de","negate":false},{"value":"que","negate":false},{"value":"el","negate":false},{"value":"propio","negate":false},{"value":"jatamí","negate":false},{"value":"pudiese","negate":false},{"value":"presentar","negate":false},{"value":"su","negate":false},{"value":"renuncia","negate":false},{"value":"abtaji","negate":false},{"value":"recordó","negate":false},{"value":"las","negate":false},{"value":"antiguas","negate":false},{"value":"amenazas","negate":false},{"value":"de","negate":false},{"value":"jatamí","negate":false},{"value":"y","negate":false},{"value":"subvrayó","negate":false},{"value":"que","negate":false},{"value":"un","negate":false},{"value":"cierto","negate":false},{"value":"número","negate":false},{"value":"de","negate":false},{"value":"ministros","negate":false},{"value":"y","negate":false},{"value":"vicepresidentes","negate":false},{"value":"han","negate":false},{"value":"dimitido","negate":false},{"value":"pero","negate":false},{"value":"a","negate":false},{"value":"la","negate":false},{"value":"vez","negate":false},{"value":"dio","negate":false},{"value":"a","negate":false},{"value":"entender","negate":false},{"value":"que","negate":false},{"value":"la","negate":false},{"value":"presentación","negate":false},{"value":"de","negate":false},{"value":"la","negate":false},{"value":"dimisión","negate":false},{"value":"no","negate":true},{"value":"es","negate":false},{"value":"equivalente","negate":false},{"value":"a","negate":false},{"value":"su","negate":false},{"value":"renuncia","negate":false},{"value":"automática","negate":false},{"value":"explicó","negate":false},{"value":"a","negate":false},{"value":"este","negate":false},{"value":"respecto","negate":false},{"value":"que","negate":false},{"value":"antes","negate":false},{"value":"de","negate":false},{"value":"hacer","negate":false},{"value":"efectiva","negate":false},{"value":"su","negate":false},{"value":"salida","negate":false},{"value":"del","negate":false},{"value":"gobierno","negate":false},{"value":"los","negate":false},{"value":"dimisionarios","negate":false},{"value":"esperarán","negate":false},{"value":"el","negate":false},{"value":"resultado","negate":false},{"value":"de","negate":false},{"value":"las","negate":false},{"value":"deliberaciones","negate":false},{"value":"mantenidas","negate":false},{"value":"por","negate":false},{"value":"el","negate":false},{"value":"consejo","negate":false},{"value":"de","negate":false},{"value":"guardianes","negate":false},{"value":"de","negate":false},{"value":"la","negate":false},{"value":"constitución","negate":false},{"value":"núcleo","negate":false},{"value":"duro","negate":false},{"value":"de","negate":false},{"value":"los","negate":false},{"value":"inmovilistas","negate":false},{"value":"se","negate":false},{"value":"trata","negate":false},{"value":"por","negate":false},{"value":"tanto","negate":false},{"value":"de","negate":false},{"value":"unas","negate":false},{"value":"dimisiones","negate":false},{"value":"condicionadas","negate":false},{"value":"o","negate":false},{"value":"en","negate":false},{"value":"suspenso","negate":false},{"value":"pero","negate":false},{"value":"que","negate":false},{"value":"sirven","negate":false},{"value":"para","negate":false},{"value":"aumentar","negate":false},{"value":"la","negate":false},{"value":"presión","negate":false},{"value":"sobre","negate":false},{"value":"el","negate":false},{"value":"consejo","negate":false},{"value":"de","negate":false},{"value":"guardianes","negate":false},{"value":"en","negate":false},{"value":"el","negate":false},{"value":"pulso","negate":false},{"value":"que","negate":false},{"value":"ortodoxos","negate":false},{"value":"y","negate":false},{"value":"liberales","negate":false},{"value":"mantienen","negate":false},{"value":"ante","negate":false},{"value":"los","negate":false},{"value":"próximos","negate":false},{"value":"comicios","negate":false},{"value":"abtahi","negate":false},{"value":"reiteró","negate":false},{"value":"la","negate":false},{"value":"amenaza","negate":false},{"value":"lanzada","negate":false},{"value":"la","negate":false},{"value":"pasada","negate":false},{"value":"semana","negate":false},{"value":"por","negate":false},{"value":"jatamí","negate":false},{"value":"de","negate":false},{"value":"una","negate":false},{"value":"dimisión","negate":false},{"value":"en","negate":false},{"value":"bloque","negate":false},{"value":"de","negate":false},{"value":"todos","negate":false},{"value":"los","negate":false},{"value":"reformistas","negate":false},{"value":"que","negate":false},{"value":"controlan","negate":false},{"value":"la","negate":false},{"value":"presidencia","negate":false},{"value":"y","negate":false},{"value":"el","negate":false},{"value":"ejecutivo","negate":false},{"value":"iraní","negate":false},{"value":"si","negate":false},{"value":"el","negate":false},{"value":"consejo","negate":false},{"value":"de","negate":false},{"value":"guardianes","negate":false},{"value":"no","negate":true},{"value":"da","negate":false},{"value":"marcha","negate":false},{"value":"atrás","negate":false},{"value":"a","negate":false},{"value":"su","negate":false},{"value":"decisión","negate":false},{"value":"de","negate":false},{"value":"veto","negate":false},{"value":"colectivo","negate":false},{"value":"cuando","negate":false},{"value":"así","negate":false},{"value":"ocurra","negate":false},{"value":"aquí","negate":false},{"value":"todo","negate":false},{"value":"el","negate":false},{"value":"mundo","negate":false},{"value":"se","negate":false},{"value":"iría","negate":false},{"value":"afirmó","negate":false},{"value":"entonces","negate":false},{"value":"el","negate":false},{"value":"presidente","negate":false},{"value":"quien","negate":false},{"value":"sin","negate":false},{"value":"embargo","negate":false},{"value":"ayer","negate":false},{"value":"insistió","negate":false},{"value":"en","negate":false},{"value":"que","negate":false},{"value":"pese","negate":false},{"value":"a","negate":false},{"value":"todo","negate":false},{"value":"él","negate":false},{"value":"sigue","negate":false},{"value":"todavía","negate":false},{"value":"en","negate":false},{"value":"su","negate":false},{"value":"puesto","negate":false},{"value":"el","negate":false},{"value":"consejo","negate":false},{"value":"de","negate":false},{"value":"guardianes","negate":false},{"value":"ha","negate":false},{"value":"anulado","negate":false},{"value":"casi","negate":false},{"value":"la","negate":false},{"value":"mitad","negate":false},{"value":"de","negate":false},{"value":"las","negate":false},{"value":"candidaturas","negate":false},{"value":"electorales","negate":false},{"value":"en","negate":false},{"value":"una","negate":false},{"value":"decisión","negate":false},{"value":"que","negate":false},{"value":"los","negate":false},{"value":"reformistas","negate":false},{"value":"tildan","negate":false},{"value":"de","negate":false},{"value":"golpe","negate":false},{"value":"de","negate":false},{"value":"estado","negate":false},{"value":"el","negate":false},{"value":"científico","negate":false},{"value":"david","negate":false},{"value":"kelly","negate":false},{"value":"declaró","negate":false},{"value":"antes","negate":false},{"value":"de","negate":false},{"value":"suicidarse","negate":false},{"value":"que","negate":false},{"value":"irak","negate":false},{"value":"tenía","negate":false},{"value":"armas","negate":false},{"value":"de","negate":false},{"value":"destrucción","negate":false},{"value":"masiva","negate":false},{"value":"emili","negate":false},{"value":"j","negate":false},{"value":"blasco","negate":false},{"value":"corresponsal","negate":false},{"value":"londres","negate":false},{"value":"a","negate":false},{"value":"una","negate":false},{"value":"semana","negate":false},{"value":"de","negate":false},{"value":"la","negate":false},{"value":"publicación","negate":false},{"value":"del","negate":false},{"value":"informe","negate":false},{"value":"hutton","negate":false},{"value":"la","negate":false},{"value":"bbc","negate":false},{"value":"difundió","negate":false},{"value":"anoche","negate":false},{"value":"una","negate":false},{"value":"entrevista","negate":false},{"value":"nunca","negate":false},{"value":"emitida","negate":false},{"value":"en","negate":false},{"value":"la","negate":false},{"value":"que","negate":false},{"value":"el","negate":false},{"value":"experto","negate":false},{"value":"de","negate":false},{"value":"armas","negate":false},{"value":"david","negate":false},{"value":"kelly","negate":false},{"value":"aseguraba","negate":false},{"value":"que","negate":false},{"value":"irak","negate":false},{"value":"era","negate":false},{"value":"una","negate":false},{"value":"amenaza","negate":false},{"value":"inmediata","negate":false},{"value":"y","negate":false},{"value":"confirmaba","negate":false},{"value":"que","negate":false},{"value":"sadam","negate":false},{"value":"husein","negate":false},{"value":"tenía","negate":false},{"value":"armas","negate":false},{"value":"de","negate":false},{"value":"destrucción","negate":false},{"value":"masiva","negate":false},{"value":"el","negate":false},{"value":"suicidio","negate":false},{"value":"de","negate":false},{"value":"kelly","negate":false},{"value":"tras","negate":false},{"value":"la","negate":false},{"value":"acusación","negate":false},{"value":"lanzada","negate":false},{"value":"por","negate":false},{"value":"la","negate":false},{"value":"bbc","negate":false},{"value":"de","negate":false},{"value":"que","negate":false},{"value":"tony","negate":false},{"value":"blair","negate":false},{"value":"exageró","negate":false},{"value":"el","negate":false},{"value":"riesto","negate":false},{"value":"que","negate":false},{"value":"suponía","negate":false},{"value":"irak","negate":false},{"value":"abrieron","negate":false},{"value":"una","negate":false},{"value":"crisis","negate":false},{"value":"política","negate":false},{"value":"cuyas","negate":false},{"value":"dimensiones","negate":false},{"value":"debería","negate":false},{"value":"marcar","negate":false},{"value":"el","negate":false},{"value":"informe","negate":false},{"value":"del","negate":false},{"value":"juez","negate":false},{"value":"hutton","negate":false},{"value":"el","negate":false},{"value":"documental","negate":false},{"value":"de","negate":false},{"value":"panorama","negate":false},{"value":"emitido","negate":false},{"value":"anoche","negate":false},{"value":"pareció","negate":false},{"value":"reforzar","negate":false},{"value":"ciertos","negate":false},{"value":"aspectos","negate":false},{"value":"de","negate":false},{"value":"la","negate":false},{"value":"posición","negate":false},{"value":"del","negate":false},{"value":"gobierno","negate":false},{"value":"aunque","negate":false},{"value":"tampoco","negate":false},{"value":"le","negate":false},{"value":"dio","negate":false},{"value":"toda","negate":false},{"value":"la","negate":false},{"value":"razón","negate":false},{"value":"al","negate":false},{"value":"tiempo","negate":false},{"value":"que","negate":false},{"value":"censuraba","negate":false},{"value":"algunos","negate":false},{"value":"comportamientos","negate":false},{"value":"de","negate":false},{"value":"la","negate":false},{"value":"bbc","negate":false},{"value":"en","negate":false},{"value":"un","negate":false},{"value":"ejercicio","negate":false},{"value":"de","negate":false},{"value":"pluralidad","negate":false},{"value":"interna","negate":false},{"value":"difícilmente","negate":false},{"value":"imaginable","negate":false},{"value":"en","negate":false},{"value":"otras","negate":false},{"value":"radiotelevisiones","negate":false},{"value":"públicas","negate":false},{"value":"la","negate":false},{"value":"emisión","negate":false},{"value":"fue","negate":false},{"value":"elaborada","negate":false},{"value":"por","negate":false},{"value":"la","negate":false},{"value":"redacción","negate":false},{"value":"de","negate":false},{"value":"programas","negate":false},{"value":"informativos","negate":false},{"value":"de","negate":false},{"value":"la","negate":false},{"value":"bbc","negate":false},{"value":"en","negate":false},{"value":"lo","negate":false},{"value":"que","negate":false},{"value":"algunos","negate":false},{"value":"comentaristas","negate":false},{"value":"han","negate":false},{"value":"visto","negate":false},{"value":"una","negate":false},{"value":"batalla","negate":false},{"value":"interna","negate":false},{"value":"con-","negate":false},{"value":"tra","negate":false},{"value":"la","negate":false},{"value":"redacción","negate":false},{"value":"de","negate":false},{"value":"informativos","negate":false},{"value":"diarios","negate":false},{"value":"de","negate":false},{"value":"la","negate":false},{"value":"que","negate":false},{"value":"formaba","negate":false},{"value":"parte","negate":false},{"value":"el","negate":false},{"value":"programa","negate":false},{"value":"today","negate":false},{"value":"de","negate":false},{"value":"andrew","negate":false},{"value":"gilligan","negate":false},{"value":"desencadenante","negate":false},{"value":"de","negate":false},{"value":"la","negate":false},{"value":"polémica","negate":false},{"value":"la","negate":false},{"value":"entrevista","negate":false},{"value":"con","negate":false},{"value":"kelly","negate":false},{"value":"fue","negate":false},{"value":"realizada","negate":false},{"value":"en","negate":false},{"value":"octubre","negate":false},{"value":"de","negate":false},{"value":"2002","negate":false},{"value":"un","negate":false},{"value":"mes","negate":false},{"value":"después","negate":false},{"value":"de","negate":false},{"value":"que","negate":false},{"value":"blair","negate":false},{"value":"presentara","negate":false},{"value":"el","negate":false},{"value":"polémico","negate":false},{"value":"informe","negate":false},{"value":"en","negate":false},{"value":"el","negate":false},{"value":"que","negate":false},{"value":"se","negate":false},{"value":"aseguraba","negate":false},{"value":"que","negate":false},{"value":"irak","negate":false},{"value":"suponía","negate":false},{"value":"un","negate":false},{"value":"riesgo","negate":false},{"value":"para","negate":false},{"value":"la","negate":false},{"value":"paz","negate":false},{"value":"y","negate":false},{"value":"podía","negate":false},{"value":"emplear","negate":false},{"value":"sus","negate":false},{"value":"armas","negate":false},{"value":"de","negate":false},{"value":"destrucción","negate":false},{"value":"masiva","negate":false},{"value":"en","negate":false},{"value":"apenas","negate":false},{"value":"45","negate":false},{"value":"minutos","negate":false},{"value":"en","negate":false},{"value":"esa","negate":false},{"value":"entrevista","negate":false},{"value":"cuya","negate":false},{"value":"no","negate":true},{"value":"difusión","negate":false},{"value":"en","negate":false},{"value":"todo","negate":false},{"value":"este","negate":false},{"value":"tiempo","negate":false},{"value":"no","negate":true},{"value":"ha","negate":false},{"value":"sido","negate":false},{"value":"justificada","negate":false},{"value":"por","negate":false},{"value":"la","negate":false},{"value":"dirección","negate":false},{"value":"de","negate":false},{"value":"la","negate":false},{"value":"bbc","negate":false},{"value":"kelly","negate":false},{"value":"daba","negate":false},{"value":"la","negate":false},{"value":"razón","negate":false},{"value":"al","negate":false},{"value":"gobierno","negate":false},{"value":"en","negate":false},{"value":"el","negate":false},{"value":"sentido","negate":false},{"value":"de","negate":false},{"value":"que","negate":false},{"value":"sadam","negate":false},{"value":"era","negate":false},{"value":"una","negate":false},{"value":"amenaza","negate":false},{"value":"inmediata","negate":false},{"value":"pero","negate":false},{"value":"venía","negate":false},{"value":"a","negate":false},{"value":"negar","negate":false},{"value":"que","negate":false},{"value":"estuviera","negate":false},{"value":"en","negate":false},{"value":"disposición","negate":false},{"value":"de","negate":false},{"value":"sus","negate":false},{"value":"armas","negate":false},{"value":"de","negate":false},{"value":"destrucción","negate":false},{"value":"masiva","negate":false},{"value":"en","negate":false},{"value":"45","negate":false},{"value":"minutos","negate":false},{"value":"ya","negate":false},{"value":"que","negate":false},{"value":"en","negate":false},{"value":"su","negate":false},{"value":"opinión","negate":false},{"value":"éstas","negate":false},{"value":"sólo","negate":false},{"value":"podían","negate":false},{"value":"estar","negate":false},{"value":"operativas","negate":false},{"value":"en","negate":false},{"value":"cuestión","negate":false},{"value":"de","negate":false},{"value":"días","negate":false},{"value":"o","negate":false},{"value":"semanas","negate":false},{"value":"el","negate":false},{"value":"programa","negate":false},{"value":"llegó","negate":false},{"value":"a","negate":false},{"value":"afirmar","negate":false},{"value":"que","negate":false},{"value":"gilligan","negate":false},{"value":"estaba","negate":false},{"value":"equivocado","negate":false},{"value":"cuando","negate":false},{"value":"dijo","negate":false},{"value":"que","negate":false},{"value":"downing","negate":false},{"value":"street","negate":false},{"value":"ordenó","negate":false},{"value":"a","negate":false},{"value":"los","negate":false},{"value":"servicios","negate":false},{"value":"de","negate":false},{"value":"inteligencia","negate":false},{"value":"que","negate":false},{"value":"exagerasen","negate":false},{"value":"los","negate":false},{"value":"datos","negate":false}],"words":["abandonar","puesto","renuncia","aumentado","presión","protestar","impedir","solución","crisis","propio","renuncia","amenazas","cierto","renuncia","duro","aumentar","presión","amenaza","puesto","golpe","destrucción","amenaza","destrucción","suicidio","acusación","crisis","tiempo","batalla","polémico","riesgo","paz","destrucción","tiempo","sentido","amenaza","negar","destrucción","equivocado","abandonar","puesto","renuncia","aumentado","presión","protestar","impedir","solución","crisis","propio","renuncia","amenazas","cierto","renuncia","duro","aumentar","presión","amenaza","puesto","golpe","destrucción","amenaza","destrucción","suicidio","acusación","crisis","tiempo","batalla","polémico","riesgo","paz","destrucción","tiempo","sentido","amenaza","negar","destrucción","equivocado","abandonar","puesto","renuncia","aumentado","presión","protestar","impedir","solución","crisis","propio","renuncia","amenazas","cierto","renuncia","duro","aumentar","presión","amenaza","puesto","golpe","destrucción","amenaza","destrucción","suicidio","acusación","crisis","tiempo","batalla","polémico","riesgo","paz","destrucción","tiempo","sentido","amenaza","negar","destrucción","equivocado"],"positive":["aumentado","solución","propio","cierto","aumentar","paz","sentido","aumentado","solución","propio","cierto","aumentar","paz","sentido","aumentado","solución","propio","cierto","aumentar","paz","sentido"],"negative":["abandonar","puesto","renuncia","presión","protestar","impedir","crisis","renuncia","amenazas","renuncia","duro","presión","amenaza","puesto","golpe","destrucción","amenaza","destrucción","suicidio","acusación","crisis","tiempo","batalla","polémico","riesgo","destrucción","tiempo","amenaza","negar","destrucción","equivocado","abandonar","puesto","renuncia","presión","protestar","impedir","crisis","renuncia","amenazas","renuncia","duro","presión","amenaza","puesto","golpe","destrucción","amenaza","destrucción","suicidio","acusación","crisis","tiempo","batalla","polémico","riesgo","destrucción","tiempo","amenaza","negar","destrucción","equivocado","abandonar","puesto","renuncia","presión","protestar","impedir","crisis","renuncia","amenazas","renuncia","duro","presión","amenaza","puesto","golpe","destrucción","amenaza","destrucción","suicidio","acusación","crisis","tiempo","batalla","polémico","riesgo","destrucción","tiempo","amenaza","negar","destrucción","equivocado"]},"sentiment_analysis_score":-150,"sentiment_analysis_comparative":-0.07}