{"_id":"5d9bfd45eb6336f31831133f","page":0,"fullpage":false,"headline":"Miraos en el espejo","date":"2018-06-09T13:36:50.995Z","content":"Miraos en el espejo\n\n\n\t\t\t\t\t\tConsulte la portada de EL PAÍS, Edición Europa, del 8 de octubre\n »\t\t\t\t\t\nEn la superficie, todo parece jugar a favor. Europa hace piña ante las asechanzas comerciales de Donald Trump, aunque con una relativa salvedad italiana. Reafirma la lucha contra el cambio climático y a favor de la distensión con Irán. Sigue firme contra las intervenciones militares, digitales y de espionaje de Vladímir Putin, aunque con la relativa salvedad italiana. Y los Veintisiete han alcanzado un increíble e imprevisto nivel de cohesión frente a la suicida escapada de Reino Unido.\nEsa fortaleza proviene del triunfo de una primavera. Tormentosa, pero indudable. Política, porque a diferencia de EE UU, los populismos —a excepción de la salvedad de Italia, a medias de Austria— han sido electoralmente derrotados. Económica, porque llevamos cuatro años largos de crecimiento económico sostenido. Social, porque las encuestas —como el último Eurobarómetro— acreditan una renacida fortaleza europeísta en todas partes, con la salvedad italiana. Y, sin embargo, las dos asignaturas pendientes para la cumbre de final de junio (inmigración, reforzamiento del euro) parecen cada día más y más escarpadas. Quizá porque en la superficie el populismo no triunfó, pero se ha enquistado por debajo en algunos partidos tradicionales, a los que horada con su ponzoña ideológica antiliberal.\nNos escandaliza la pinza de los extremismos italianos coligados, la única realmente abiertamente triunfadora en las urnas. Pero ya hace tiempo, es un ejemplo, que el pequeño y liberalísimo país de Borgen huele a podrido: en Dinamarca se recortan las ayudas a los refugiados, se piden cuotas restrictivas a los inmigrantes (cierta supuesta izquierda), se propugna disparar a las pateras (la ultraderecha), se anhelan los controles fronterizos. Quizá ocurre también que las secuelas sociales de la crisis se desperdigan a ritmo lento, con retraso: la frustración aspiracional de la perjudicada clase media, antes solidaria y ahora (temblemos) introspectiva; la falta de horizontes para las clases trabajadoras abocadas al precariado y la desigualdad como consecuencia del exceso austeritario; el desgaste de una izquierda convencional que debió priorizar (por minoritaria) cómo minimizar la recesión, en vez de combatirla; la fisura (o ruptura) del contrato social de los 30 años gloriosos, que cohonestaba un capitalismo de rostro humano con el más generoso Estado del bienestar de la historia.\nAsí que la fragmentación económica de la era de la crisis ha derivado en una múltiple (e inédita) amenaza divisoria de la Unión. Hay un frente nacionalista xenófobo e iliberal apalancado en los socios orientales postsoviéticos (aunque no solo en ellos); hay un bloque nórdico encabezado por Holanda que denigra la recuperación de la solidaridad Norte/Sur (y la arquitectura de la unión monetaria ante próximas recesiones); hay un clamor transversal reaccionario en pro del egoísmo, contra los fugitivos africanos de la pobreza.\nY, sin embargo, la partida frente a la reacción, el populismo iliberal, la eurohostilidad y la endogamia nacional no está perdida. Porque seguramente por vez primera, los Gobiernos de los Veintisiete deben ser transparentes, responsables, y mirarse ante el espejo. ¿Por qué? Porque el envite proteccionista de Donald Trump les obliga a definirse sobre la necesidad de aumentar su apuesta por la defensa común (y el comercio, y la fiscalidad a las tecnológicas, y tantas otras cosas). Porque la crisis humanitaria mediterránea les conmina a elegir entre la represión y el fomento del crecimiento económico subsahariano. Porque la próxima —aunque no sea inmediata— normalización de la política monetaria (el fin del expansionismo y los tipos cero) reclama políticas presupuestarias que la compensen.\nUn país últimamente periférico tiene cartas para este pulso: la defensa de la cohesión desde la seriedad fiscal; la reconstrucción de la conjura mediterránea frente a sus escapistas; la apuesta liberal contra los autócratas. Esta España, más comprometida y amable.\n \n NEWSLETTER \n Recibe el boletín de Internacional \nEl revolucionario sistema educativo va más allá de la escuela: propone cambiar el entorno del niño para que sea un adulto libre. La decoración es esencial.","url":"https://elpais.com/internacional/2018/06/09/actualidad/1528577106_671278.html","newspaper":"elpais","scraper_id":"scraper_home","id":"a059e5e7-b5d0-4b44-4a61-1e102b5ab4cc","sentiment_analysis_obj":{"score":0,"comparative":0,"tokens":[{"value":"miraos","negate":false},{"value":"en","negate":false},{"value":"el","negate":false},{"value":"espejo","negate":false},{"value":"consulte","negate":false},{"value":"la","negate":false},{"value":"portada","negate":false},{"value":"de","negate":false},{"value":"el","negate":false},{"value":"país","negate":false},{"value":"edición","negate":false},{"value":"europa","negate":false},{"value":"del","negate":false},{"value":"8","negate":false},{"value":"de","negate":false},{"value":"octubre","negate":false},{"value":"»","negate":false},{"value":"en","negate":false},{"value":"la","negate":false},{"value":"superficie","negate":false},{"value":"todo","negate":false},{"value":"parece","negate":false},{"value":"jugar","negate":false},{"value":"a","negate":false},{"value":"favor","negate":false},{"value":"europa","negate":false},{"value":"hace","negate":false},{"value":"piña","negate":false},{"value":"ante","negate":false},{"value":"las","negate":false},{"value":"asechanzas","negate":false},{"value":"comerciales","negate":false},{"value":"de","negate":false},{"value":"donald","negate":false},{"value":"trump","negate":false},{"value":"aunque","negate":false},{"value":"con","negate":false},{"value":"una","negate":false},{"value":"relativa","negate":false},{"value":"salvedad","negate":false},{"value":"italiana","negate":false},{"value":"reafirma","negate":false},{"value":"la","negate":false},{"value":"lucha","negate":false},{"value":"contra","negate":false},{"value":"el","negate":false},{"value":"cambio","negate":false},{"value":"climático","negate":false},{"value":"y","negate":false},{"value":"a","negate":false},{"value":"favor","negate":false},{"value":"de","negate":false},{"value":"la","negate":false},{"value":"distensión","negate":false},{"value":"con","negate":false},{"value":"irán","negate":false},{"value":"sigue","negate":false},{"value":"firme","negate":false},{"value":"contra","negate":false},{"value":"las","negate":false},{"value":"intervenciones","negate":false},{"value":"militares","negate":false},{"value":"digitales","negate":false},{"value":"y","negate":false},{"value":"de","negate":false},{"value":"espionaje","negate":false},{"value":"de","negate":false},{"value":"vladímir","negate":false},{"value":"putin","negate":false},{"value":"aunque","negate":false},{"value":"con","negate":false},{"value":"la","negate":false},{"value":"relativa","negate":false},{"value":"salvedad","negate":false},{"value":"italiana","negate":false},{"value":"y","negate":false},{"value":"los","negate":false},{"value":"veintisiete","negate":false},{"value":"han","negate":false},{"value":"alcanzado","negate":false},{"value":"un","negate":false},{"value":"increíble","negate":false},{"value":"e","negate":false},{"value":"imprevisto","negate":false},{"value":"nivel","negate":false},{"value":"de","negate":false},{"value":"cohesión","negate":false},{"value":"frente","negate":false},{"value":"a","negate":false},{"value":"la","negate":false},{"value":"suicida","negate":false},{"value":"escapada","negate":false},{"value":"de","negate":false},{"value":"reino","negate":false},{"value":"unido","negate":false},{"value":"esa","negate":false},{"value":"fortaleza","negate":false},{"value":"proviene","negate":false},{"value":"del","negate":false},{"value":"triunfo","negate":false},{"value":"de","negate":false},{"value":"una","negate":false},{"value":"primavera","negate":false},{"value":"tormentosa","negate":false},{"value":"pero","negate":false},{"value":"indudable","negate":false},{"value":"política","negate":false},{"value":"porque","negate":false},{"value":"a","negate":false},{"value":"diferencia","negate":false},{"value":"de","negate":false},{"value":"ee","negate":false},{"value":"uu","negate":false},{"value":"los","negate":false},{"value":"populismos","negate":false},{"value":"—a","negate":false},{"value":"excepción","negate":false},{"value":"de","negate":false},{"value":"la","negate":false},{"value":"salvedad","negate":false},{"value":"de","negate":false},{"value":"italia","negate":false},{"value":"a","negate":false},{"value":"medias","negate":false},{"value":"de","negate":false},{"value":"austria—","negate":false},{"value":"han","negate":false},{"value":"sido","negate":false},{"value":"electoralmente","negate":false},{"value":"derrotados","negate":false},{"value":"económica","negate":false},{"value":"porque","negate":false},{"value":"llevamos","negate":false},{"value":"cuatro","negate":false},{"value":"años","negate":false},{"value":"largos","negate":false},{"value":"de","negate":false},{"value":"crecimiento","negate":false},{"value":"económico","negate":false},{"value":"sostenido","negate":false},{"value":"social","negate":false},{"value":"porque","negate":false},{"value":"las","negate":false},{"value":"encuestas","negate":false},{"value":"—como","negate":false},{"value":"el","negate":false},{"value":"último","negate":false},{"value":"eurobarómetro—","negate":false},{"value":"acreditan","negate":false},{"value":"una","negate":false},{"value":"renacida","negate":false},{"value":"fortaleza","negate":false},{"value":"europeísta","negate":false},{"value":"en","negate":false},{"value":"todas","negate":false},{"value":"partes","negate":false},{"value":"con","negate":false},{"value":"la","negate":false},{"value":"salvedad","negate":false},{"value":"italiana","negate":false},{"value":"y","negate":false},{"value":"sin","negate":false},{"value":"embargo","negate":false},{"value":"las","negate":false},{"value":"dos","negate":false},{"value":"asignaturas","negate":false},{"value":"pendientes","negate":false},{"value":"para","negate":false},{"value":"la","negate":false},{"value":"cumbre","negate":false},{"value":"de","negate":false},{"value":"final","negate":false},{"value":"de","negate":false},{"value":"junio","negate":false},{"value":"inmigración","negate":false},{"value":"reforzamiento","negate":false},{"value":"del","negate":false},{"value":"euro","negate":false},{"value":"parecen","negate":false},{"value":"cada","negate":false},{"value":"día","negate":false},{"value":"más","negate":false},{"value":"y","negate":false},{"value":"más","negate":false},{"value":"escarpadas","negate":false},{"value":"quizá","negate":false},{"value":"porque","negate":false},{"value":"en","negate":false},{"value":"la","negate":false},{"value":"superficie","negate":false},{"value":"el","negate":false},{"value":"populismo","negate":false},{"value":"no","negate":true},{"value":"triunfó","negate":false},{"value":"pero","negate":false},{"value":"se","negate":false},{"value":"ha","negate":false},{"value":"enquistado","negate":false},{"value":"por","negate":false},{"value":"debajo","negate":false},{"value":"en","negate":false},{"value":"algunos","negate":false},{"value":"partidos","negate":false},{"value":"tradicionales","negate":false},{"value":"a","negate":false},{"value":"los","negate":false},{"value":"que","negate":false},{"value":"horada","negate":false},{"value":"con","negate":false},{"value":"su","negate":false},{"value":"ponzoña","negate":false},{"value":"ideológica","negate":false},{"value":"antiliberal","negate":false},{"value":"nos","negate":false},{"value":"escandaliza","negate":false},{"value":"la","negate":false},{"value":"pinza","negate":false},{"value":"de","negate":false},{"value":"los","negate":false},{"value":"extremismos","negate":false},{"value":"italianos","negate":false},{"value":"coligados","negate":false},{"value":"la","negate":false},{"value":"única","negate":false},{"value":"realmente","negate":false},{"value":"abiertamente","negate":false},{"value":"triunfadora","negate":false},{"value":"en","negate":false},{"value":"las","negate":false},{"value":"urnas","negate":false},{"value":"pero","negate":false},{"value":"ya","negate":false},{"value":"hace","negate":false},{"value":"tiempo","negate":false},{"value":"es","negate":false},{"value":"un","negate":false},{"value":"ejemplo","negate":false},{"value":"que","negate":false},{"value":"el","negate":false},{"value":"pequeño","negate":false},{"value":"y","negate":false},{"value":"liberalísimo","negate":false},{"value":"país","negate":false},{"value":"de","negate":false},{"value":"borgen","negate":false},{"value":"huele","negate":false},{"value":"a","negate":false},{"value":"podrido","negate":false},{"value":"en","negate":false},{"value":"dinamarca","negate":false},{"value":"se","negate":false},{"value":"recortan","negate":false},{"value":"las","negate":false},{"value":"ayudas","negate":false},{"value":"a","negate":false},{"value":"los","negate":false},{"value":"refugiados","negate":false},{"value":"se","negate":false},{"value":"piden","negate":false},{"value":"cuotas","negate":false},{"value":"restrictivas","negate":false},{"value":"a","negate":false},{"value":"los","negate":false},{"value":"inmigrantes","negate":false},{"value":"cierta","negate":false},{"value":"supuesta","negate":false},{"value":"izquierda","negate":false},{"value":"se","negate":false},{"value":"propugna","negate":false},{"value":"disparar","negate":false},{"value":"a","negate":false},{"value":"las","negate":false},{"value":"pateras","negate":false},{"value":"la","negate":false},{"value":"ultraderecha","negate":false},{"value":"se","negate":false},{"value":"anhelan","negate":false},{"value":"los","negate":false},{"value":"controles","negate":false},{"value":"fronterizos","negate":false},{"value":"quizá","negate":false},{"value":"ocurre","negate":false},{"value":"también","negate":false},{"value":"que","negate":false},{"value":"las","negate":false},{"value":"secuelas","negate":false},{"value":"sociales","negate":false},{"value":"de","negate":false},{"value":"la","negate":false},{"value":"crisis","negate":false},{"value":"se","negate":false},{"value":"desperdigan","negate":false},{"value":"a","negate":false},{"value":"ritmo","negate":false},{"value":"lento","negate":false},{"value":"con","negate":false},{"value":"retraso","negate":false},{"value":"la","negate":false},{"value":"frustración","negate":false},{"value":"aspiracional","negate":false},{"value":"de","negate":false},{"value":"la","negate":false},{"value":"perjudicada","negate":false},{"value":"clase","negate":false},{"value":"media","negate":false},{"value":"antes","negate":false},{"value":"solidaria","negate":false},{"value":"y","negate":false},{"value":"ahora","negate":false},{"value":"temblemos","negate":false},{"value":"introspectiva","negate":false},{"value":"la","negate":false},{"value":"falta","negate":false},{"value":"de","negate":false},{"value":"horizontes","negate":false},{"value":"para","negate":false},{"value":"las","negate":false},{"value":"clases","negate":false},{"value":"trabajadoras","negate":false},{"value":"abocadas","negate":false},{"value":"al","negate":false},{"value":"precariado","negate":false},{"value":"y","negate":false},{"value":"la","negate":false},{"value":"desigualdad","negate":false},{"value":"como","negate":false},{"value":"consecuencia","negate":false},{"value":"del","negate":false},{"value":"exceso","negate":false},{"value":"austeritario","negate":false},{"value":"el","negate":false},{"value":"desgaste","negate":false},{"value":"de","negate":false},{"value":"una","negate":false},{"value":"izquierda","negate":false},{"value":"convencional","negate":false},{"value":"que","negate":false},{"value":"debió","negate":false},{"value":"priorizar","negate":false},{"value":"por","negate":false},{"value":"minoritaria","negate":false},{"value":"cómo","negate":false},{"value":"minimizar","negate":false},{"value":"la","negate":false},{"value":"recesión","negate":false},{"value":"en","negate":false},{"value":"vez","negate":false},{"value":"de","negate":false},{"value":"combatirla","negate":false},{"value":"la","negate":false},{"value":"fisura","negate":false},{"value":"o","negate":false},{"value":"ruptura","negate":false},{"value":"del","negate":false},{"value":"contrato","negate":false},{"value":"social","negate":false},{"value":"de","negate":false},{"value":"los","negate":false},{"value":"30","negate":false},{"value":"años","negate":false},{"value":"gloriosos","negate":false},{"value":"que","negate":false},{"value":"cohonestaba","negate":false},{"value":"un","negate":false},{"value":"capitalismo","negate":false},{"value":"de","negate":false},{"value":"rostro","negate":false},{"value":"humano","negate":false},{"value":"con","negate":false},{"value":"el","negate":false},{"value":"más","negate":false},{"value":"generoso","negate":false},{"value":"estado","negate":false},{"value":"del","negate":false},{"value":"bienestar","negate":false},{"value":"de","negate":false},{"value":"la","negate":false},{"value":"historia","negate":false},{"value":"así","negate":false},{"value":"que","negate":false},{"value":"la","negate":false},{"value":"fragmentación","negate":false},{"value":"económica","negate":false},{"value":"de","negate":false},{"value":"la","negate":false},{"value":"era","negate":false},{"value":"de","negate":false},{"value":"la","negate":false},{"value":"crisis","negate":false},{"value":"ha","negate":false},{"value":"derivado","negate":false},{"value":"en","negate":false},{"value":"una","negate":false},{"value":"múltiple","negate":false},{"value":"e","negate":false},{"value":"inédita","negate":false},{"value":"amenaza","negate":false},{"value":"divisoria","negate":false},{"value":"de","negate":false},{"value":"la","negate":false},{"value":"unión","negate":false},{"value":"hay","negate":false},{"value":"un","negate":false},{"value":"frente","negate":false},{"value":"nacionalista","negate":false},{"value":"xenófobo","negate":false},{"value":"e","negate":false},{"value":"iliberal","negate":false},{"value":"apalancado","negate":false},{"value":"en","negate":false},{"value":"los","negate":false},{"value":"socios","negate":false},{"value":"orientales","negate":false},{"value":"postsoviéticos","negate":false},{"value":"aunque","negate":false},{"value":"no","negate":true},{"value":"solo","negate":false},{"value":"en","negate":false},{"value":"ellos","negate":false},{"value":"hay","negate":false},{"value":"un","negate":false},{"value":"bloque","negate":false},{"value":"nórdico","negate":false},{"value":"encabezado","negate":false},{"value":"por","negate":false},{"value":"holanda","negate":false},{"value":"que","negate":false},{"value":"denigra","negate":false},{"value":"la","negate":false},{"value":"recuperación","negate":false},{"value":"de","negate":false},{"value":"la","negate":false},{"value":"solidaridad","negate":false},{"value":"norte","negate":false},{"value":"sur","negate":false},{"value":"y","negate":false},{"value":"la","negate":false},{"value":"arquitectura","negate":false},{"value":"de","negate":false},{"value":"la","negate":false},{"value":"unión","negate":false},{"value":"monetaria","negate":false},{"value":"ante","negate":false},{"value":"próximas","negate":false},{"value":"recesiones","negate":false},{"value":"hay","negate":false},{"value":"un","negate":false},{"value":"clamor","negate":false},{"value":"transversal","negate":false},{"value":"reaccionario","negate":false},{"value":"en","negate":false},{"value":"pro","negate":false},{"value":"del","negate":false},{"value":"egoísmo","negate":false},{"value":"contra","negate":false},{"value":"los","negate":false},{"value":"fugitivos","negate":false},{"value":"africanos","negate":false},{"value":"de","negate":false},{"value":"la","negate":false},{"value":"pobreza","negate":false},{"value":"y","negate":false},{"value":"sin","negate":false},{"value":"embargo","negate":false},{"value":"la","negate":false},{"value":"partida","negate":false},{"value":"frente","negate":false},{"value":"a","negate":false},{"value":"la","negate":false},{"value":"reacción","negate":false},{"value":"el","negate":false},{"value":"populismo","negate":false},{"value":"iliberal","negate":false},{"value":"la","negate":false},{"value":"eurohostilidad","negate":false},{"value":"y","negate":false},{"value":"la","negate":false},{"value":"endogamia","negate":false},{"value":"nacional","negate":false},{"value":"no","negate":true},{"value":"está","negate":false},{"value":"perdida","negate":false},{"value":"porque","negate":false},{"value":"seguramente","negate":false},{"value":"por","negate":false},{"value":"vez","negate":false},{"value":"primera","negate":false},{"value":"los","negate":false},{"value":"gobiernos","negate":false},{"value":"de","negate":false},{"value":"los","negate":false},{"value":"veintisiete","negate":false},{"value":"deben","negate":false},{"value":"ser","negate":false},{"value":"transparentes","negate":false},{"value":"responsables","negate":false},{"value":"y","negate":false},{"value":"mirarse","negate":false},{"value":"ante","negate":false},{"value":"el","negate":false},{"value":"espejo","negate":false},{"value":"¿por","negate":false},{"value":"qué?","negate":false},{"value":"porque","negate":false},{"value":"el","negate":false},{"value":"envite","negate":false},{"value":"proteccionista","negate":false},{"value":"de","negate":false},{"value":"donald","negate":false},{"value":"trump","negate":false},{"value":"les","negate":false},{"value":"obliga","negate":false},{"value":"a","negate":false},{"value":"definirse","negate":false},{"value":"sobre","negate":false},{"value":"la","negate":false},{"value":"necesidad","negate":false},{"value":"de","negate":false},{"value":"aumentar","negate":false},{"value":"su","negate":false},{"value":"apuesta","negate":false},{"value":"por","negate":false},{"value":"la","negate":false},{"value":"defensa","negate":false},{"value":"común","negate":false},{"value":"y","negate":false},{"value":"el","negate":false},{"value":"comercio","negate":false},{"value":"y","negate":false},{"value":"la","negate":false},{"value":"fiscalidad","negate":false},{"value":"a","negate":false},{"value":"las","negate":false},{"value":"tecnológicas","negate":false},{"value":"y","negate":false},{"value":"tantas","negate":false},{"value":"otras","negate":false},{"value":"cosas","negate":false},{"value":"porque","negate":false},{"value":"la","negate":false},{"value":"crisis","negate":false},{"value":"humanitaria","negate":false},{"value":"mediterránea","negate":false},{"value":"les","negate":false},{"value":"conmina","negate":false},{"value":"a","negate":false},{"value":"elegir","negate":false},{"value":"entre","negate":false},{"value":"la","negate":false},{"value":"represión","negate":false},{"value":"y","negate":false},{"value":"el","negate":false},{"value":"fomento","negate":false},{"value":"del","negate":false},{"value":"crecimiento","negate":false},{"value":"económico","negate":false},{"value":"subsahariano","negate":false},{"value":"porque","negate":false},{"value":"la","negate":false},{"value":"próxima","negate":false},{"value":"—aunque","negate":false},{"value":"no","negate":true},{"value":"sea","negate":false},{"value":"inmediata—","negate":false},{"value":"normalización","negate":false},{"value":"de","negate":false},{"value":"la","negate":false},{"value":"política","negate":false},{"value":"monetaria","negate":false},{"value":"el","negate":false},{"value":"fin","negate":false},{"value":"del","negate":false},{"value":"expansionismo","negate":false},{"value":"y","negate":false},{"value":"los","negate":false},{"value":"tipos","negate":false},{"value":"cero","negate":false},{"value":"reclama","negate":false},{"value":"políticas","negate":false},{"value":"presupuestarias","negate":false},{"value":"que","negate":false},{"value":"la","negate":false},{"value":"compensen","negate":false},{"value":"un","negate":false},{"value":"país","negate":false},{"value":"últimamente","negate":false},{"value":"periférico","negate":false},{"value":"tiene","negate":false},{"value":"cartas","negate":false},{"value":"para","negate":false},{"value":"este","negate":false},{"value":"pulso","negate":false},{"value":"la","negate":false},{"value":"defensa","negate":false},{"value":"de","negate":false},{"value":"la","negate":false},{"value":"cohesión","negate":false},{"value":"desde","negate":false},{"value":"la","negate":false},{"value":"seriedad","negate":false},{"value":"fiscal","negate":false},{"value":"la","negate":false},{"value":"reconstrucción","negate":false},{"value":"de","negate":false},{"value":"la","negate":false},{"value":"conjura","negate":false},{"value":"mediterránea","negate":false},{"value":"frente","negate":false},{"value":"a","negate":false},{"value":"sus","negate":false},{"value":"escapistas","negate":false},{"value":"la","negate":false},{"value":"apuesta","negate":false},{"value":"liberal","negate":false},{"value":"contra","negate":false},{"value":"los","negate":false},{"value":"autócratas","negate":false},{"value":"esta","negate":false},{"value":"españa","negate":false},{"value":"más","negate":false},{"value":"comprometida","negate":false},{"value":"y","negate":false},{"value":"amable","negate":false},{"value":"newsletter","negate":false},{"value":"recibe","negate":false},{"value":"el","negate":false},{"value":"boletín","negate":false},{"value":"de","negate":false},{"value":"internacional","negate":false},{"value":"el","negate":false},{"value":"revolucionario","negate":false},{"value":"sistema","negate":false},{"value":"educativo","negate":false},{"value":"va","negate":false},{"value":"más","negate":false},{"value":"allá","negate":false},{"value":"de","negate":false},{"value":"la","negate":false},{"value":"escuela","negate":false},{"value":"propone","negate":false},{"value":"cambiar","negate":false},{"value":"el","negate":false},{"value":"entorno","negate":false},{"value":"del","negate":false},{"value":"niño","negate":false},{"value":"para","negate":false},{"value":"que","negate":false},{"value":"sea","negate":false},{"value":"un","negate":false},{"value":"adulto","negate":false},{"value":"libre","negate":false},{"value":"la","negate":false},{"value":"decoración","negate":false},{"value":"es","negate":false},{"value":"esencial","negate":false}],"words":["favor","lucha","favor","firme","alcanzado","increíble","suicida","unido","triunfo","crecimiento","tiempo","podrido","disparar","crisis","lento","retraso","frustración","falta","recesión","ruptura","humano","generoso","bienestar","crisis","amenaza","solo","solidaridad","egoísmo","pobreza","seguramente","aumentar","crisis","crecimiento","amable"],"positive":["favor","favor","firme","alcanzado","increíble","unido","triunfo","crecimiento","humano","generoso","bienestar","solo","solidaridad","seguramente","aumentar","crecimiento","amable"],"negative":["lucha","suicida","tiempo","podrido","disparar","crisis","lento","retraso","frustración","falta","recesión","ruptura","crisis","amenaza","egoísmo","pobreza","crisis"]},"sentiment_analysis_score":0,"sentiment_analysis_comparative":0}