{"_id":"5d9b4934eb6336f3182e1173","page":0,"fullpage":false,"headline":"Ser padres en la era del postureo","date":"2019-08-11T13:36:50.995Z","content":"Ser padres en la era del postureo\n\nCOMPARTEN UNA agencia de comunicación digital, un canal de YouTube (son más bien viejotubers), un sinfín de lo que llaman pasatiempos suicidas (publicar discos de artistas infraunderground, coleccionar muñecos vintage)… y la crianza de cuatro niños de entre 4 y 14 años. Borja Prieto y Natalia Flores, los Prieto Flores, firman ¡No solo somos padres!, un antimanual para ser padres y no perder la cabeza que recoge lemas tan necesarios como “criar a un hijo es algo natural, no un máster en gilipollez humana” o “de ser padres enloquecidos, como de las drogas, también se sale”.\n“No somos psicólogos ni pedagogos, hablamos desde todas las cagadas que hemos cometido por el camino”. El objetivo del libro es, dicen, “desprogramar a esa gente que se vuelve loca al procrear, invitarlos a relajarse y que se convenzan de que sus hijos no son Einstein ni Beyoncé, ni falta que hace. La paternidad hoy es un ecosistema lleno de miedos y ansiedades. En esa sección de libros todos son para que tu hijo duerma mejor, se alimente mejor, que sea feliz; hay tal presión que es necesaria una alternativa llena de cacas y piojos”.\nSus 150 páginas hablan sobre progenitores ecoadictos, grupos de WhatsApp de padres, ir a un restaurante o de vacaciones con niños, cómo dejar de fingir con la canguro que llegas borracho, no recriminarles que usen el móvil cuando tú estás venga a dar likes en Instagram o la importancia de seguir saliendo en pareja y mantener amigos sin hijos. Tienen cuatro, háganles caso. ","url":"https://elpais.com/elpais/2019/08/05/eps/1564998886_657683.html","newspaper":"elpais","scraper_id":"scraper_home","id":"9b309e68-1372-4591-47da-73ac9c803333","sentiment_analysis_obj":{"score":3,"comparative":0.01,"tokens":[{"value":"ser","negate":false},{"value":"padres","negate":false},{"value":"en","negate":false},{"value":"la","negate":false},{"value":"era","negate":false},{"value":"del","negate":false},{"value":"postureo","negate":false},{"value":"comparten","negate":false},{"value":"una","negate":false},{"value":"agencia","negate":false},{"value":"de","negate":false},{"value":"comunicación","negate":false},{"value":"digital","negate":false},{"value":"un","negate":false},{"value":"canal","negate":false},{"value":"de","negate":false},{"value":"youtube","negate":false},{"value":"son","negate":false},{"value":"más","negate":false},{"value":"bien","negate":false},{"value":"viejotubers","negate":false},{"value":"un","negate":false},{"value":"sinfín","negate":false},{"value":"de","negate":false},{"value":"lo","negate":false},{"value":"que","negate":false},{"value":"llaman","negate":false},{"value":"pasatiempos","negate":false},{"value":"suicidas","negate":false},{"value":"publicar","negate":false},{"value":"discos","negate":false},{"value":"de","negate":false},{"value":"artistas","negate":false},{"value":"infraunderground","negate":false},{"value":"coleccionar","negate":false},{"value":"muñecos","negate":false},{"value":"vintage","negate":false},{"value":"…","negate":false},{"value":"y","negate":false},{"value":"la","negate":false},{"value":"crianza","negate":false},{"value":"de","negate":false},{"value":"cuatro","negate":false},{"value":"niños","negate":false},{"value":"de","negate":false},{"value":"entre","negate":false},{"value":"4","negate":false},{"value":"y","negate":false},{"value":"14","negate":false},{"value":"años","negate":false},{"value":"borja","negate":false},{"value":"prieto","negate":false},{"value":"y","negate":false},{"value":"natalia","negate":false},{"value":"flores","negate":false},{"value":"los","negate":false},{"value":"prieto","negate":false},{"value":"flores","negate":false},{"value":"firman","negate":false},{"value":"¡no","negate":false},{"value":"solo","negate":false},{"value":"somos","negate":false},{"value":"padres","negate":false},{"value":"un","negate":false},{"value":"antimanual","negate":false},{"value":"para","negate":false},{"value":"ser","negate":false},{"value":"padres","negate":false},{"value":"y","negate":false},{"value":"no","negate":true},{"value":"perder","negate":false},{"value":"la","negate":false},{"value":"cabeza","negate":false},{"value":"que","negate":false},{"value":"recoge","negate":false},{"value":"lemas","negate":false},{"value":"tan","negate":false},{"value":"necesarios","negate":false},{"value":"como","negate":false},{"value":"“criar","negate":false},{"value":"a","negate":false},{"value":"un","negate":false},{"value":"hijo","negate":false},{"value":"es","negate":false},{"value":"algo","negate":false},{"value":"natural","negate":false},{"value":"no","negate":true},{"value":"un","negate":false},{"value":"máster","negate":false},{"value":"en","negate":false},{"value":"gilipollez","negate":false},{"value":"humana”","negate":false},{"value":"o","negate":false},{"value":"“de","negate":false},{"value":"ser","negate":false},{"value":"padres","negate":false},{"value":"enloquecidos","negate":false},{"value":"como","negate":false},{"value":"de","negate":false},{"value":"las","negate":false},{"value":"drogas","negate":false},{"value":"también","negate":false},{"value":"se","negate":false},{"value":"sale”","negate":false},{"value":"“no","negate":false},{"value":"somos","negate":false},{"value":"psicólogos","negate":false},{"value":"ni","negate":false},{"value":"pedagogos","negate":false},{"value":"hablamos","negate":false},{"value":"desde","negate":false},{"value":"todas","negate":false},{"value":"las","negate":false},{"value":"cagadas","negate":false},{"value":"que","negate":false},{"value":"hemos","negate":false},{"value":"cometido","negate":false},{"value":"por","negate":false},{"value":"el","negate":false},{"value":"camino”","negate":false},{"value":"el","negate":false},{"value":"objetivo","negate":false},{"value":"del","negate":false},{"value":"libro","negate":false},{"value":"es","negate":false},{"value":"dicen","negate":false},{"value":"“desprogramar","negate":false},{"value":"a","negate":false},{"value":"esa","negate":false},{"value":"gente","negate":false},{"value":"que","negate":false},{"value":"se","negate":false},{"value":"vuelve","negate":false},{"value":"loca","negate":false},{"value":"al","negate":false},{"value":"procrear","negate":false},{"value":"invitarlos","negate":false},{"value":"a","negate":false},{"value":"relajarse","negate":false},{"value":"y","negate":false},{"value":"que","negate":false},{"value":"se","negate":false},{"value":"convenzan","negate":false},{"value":"de","negate":false},{"value":"que","negate":false},{"value":"sus","negate":false},{"value":"hijos","negate":false},{"value":"no","negate":true},{"value":"son","negate":false},{"value":"einstein","negate":false},{"value":"ni","negate":false},{"value":"beyoncé","negate":false},{"value":"ni","negate":false},{"value":"falta","negate":false},{"value":"que","negate":false},{"value":"hace","negate":false},{"value":"la","negate":false},{"value":"paternidad","negate":false},{"value":"hoy","negate":false},{"value":"es","negate":false},{"value":"un","negate":false},{"value":"ecosistema","negate":false},{"value":"lleno","negate":false},{"value":"de","negate":false},{"value":"miedos","negate":false},{"value":"y","negate":false},{"value":"ansiedades","negate":false},{"value":"en","negate":false},{"value":"esa","negate":false},{"value":"sección","negate":false},{"value":"de","negate":false},{"value":"libros","negate":false},{"value":"todos","negate":false},{"value":"son","negate":false},{"value":"para","negate":false},{"value":"que","negate":false},{"value":"tu","negate":false},{"value":"hijo","negate":false},{"value":"duerma","negate":false},{"value":"mejor","negate":false},{"value":"se","negate":false},{"value":"alimente","negate":false},{"value":"mejor","negate":false},{"value":"que","negate":false},{"value":"sea","negate":false},{"value":"feliz","negate":false},{"value":"hay","negate":false},{"value":"tal","negate":false},{"value":"presión","negate":false},{"value":"que","negate":false},{"value":"es","negate":false},{"value":"necesaria","negate":false},{"value":"una","negate":false},{"value":"alternativa","negate":false},{"value":"llena","negate":false},{"value":"de","negate":false},{"value":"cacas","negate":false},{"value":"y","negate":false},{"value":"piojos”","negate":false},{"value":"sus","negate":false},{"value":"150","negate":false},{"value":"páginas","negate":false},{"value":"hablan","negate":false},{"value":"sobre","negate":false},{"value":"progenitores","negate":false},{"value":"ecoadictos","negate":false},{"value":"grupos","negate":false},{"value":"de","negate":false},{"value":"whatsapp","negate":false},{"value":"de","negate":false},{"value":"padres","negate":false},{"value":"ir","negate":false},{"value":"a","negate":false},{"value":"un","negate":false},{"value":"restaurante","negate":false},{"value":"o","negate":false},{"value":"de","negate":false},{"value":"vacaciones","negate":false},{"value":"con","negate":false},{"value":"niños","negate":false},{"value":"cómo","negate":false},{"value":"dejar","negate":false},{"value":"de","negate":false},{"value":"fingir","negate":false},{"value":"con","negate":false},{"value":"la","negate":false},{"value":"canguro","negate":false},{"value":"que","negate":false},{"value":"llegas","negate":false},{"value":"borracho","negate":false},{"value":"no","negate":true},{"value":"recriminarles","negate":false},{"value":"que","negate":false},{"value":"usen","negate":false},{"value":"el","negate":false},{"value":"móvil","negate":false},{"value":"cuando","negate":false},{"value":"tú","negate":false},{"value":"estás","negate":false},{"value":"venga","negate":false},{"value":"a","negate":false},{"value":"dar","negate":false},{"value":"likes","negate":false},{"value":"en","negate":false},{"value":"instagram","negate":false},{"value":"o","negate":false},{"value":"la","negate":false},{"value":"importancia","negate":false},{"value":"de","negate":false},{"value":"seguir","negate":false},{"value":"saliendo","negate":false},{"value":"en","negate":false},{"value":"pareja","negate":false},{"value":"y","negate":false},{"value":"mantener","negate":false},{"value":"amigos","negate":false},{"value":"sin","negate":false},{"value":"hijos","negate":false},{"value":"tienen","negate":false},{"value":"cuatro","negate":false},{"value":"háganles","negate":false},{"value":"caso","negate":false}],"words":["crianza","solo","perder","natural","loca","falta","mejor","mejor","feliz","presión","fingir","borracho","venga","importancia"],"positive":["crianza","perder","natural","mejor","mejor","feliz","importancia"],"negative":["solo","loca","falta","presión","fingir","borracho","venga"]},"sentiment_analysis_score":3,"sentiment_analysis_comparative":0.01}