{"_id":"5da87001eb6336f31861b5b6","page":0,"fullpage":false,"headline":"Un cumpleaños minado","date":"2002-01-26T14:36:50.995Z","content":"Un cumpleaños minado\n\nParís, años veinte. Antonin Artaud y Roger Vitrac, socios, amigos dentro de lo que cabe y rendidos admiradores del creador del Padre Ubú, fundan el Théâtre Alfred Jarry con el propósito de poner en escena piezas que golpeen al espectador en plena línea de flotación. Entre las que Artaud montó antes de que su ideario y su empresa naufragaran figura Víctor o los niños al poder, tragicomedia en la que Vitrac esboza algunas de las claves de lo que el director dio en llamar Teatro de la Crueldad.\nEl protagonista de Víctor es un niño extremadamente precoz y malévolo, que en su noveno cumpleaños decide dinamitar la frágil armonía familiar. Lo primero que hace es chantajear a la criada, que se acuesta en secreto con su padre, para que le conceda los mismos favores que a éste, y después se dedica a sacar los trapos sucios de sus progenitores y de los invitados a su fiesta. El truco, lo que hace que la obra no se resuelva con un par de bofetones bien dados, estriba en que, como el pequeño nunca ha roto un plato, ahora que deja caer toda la vajilla de golpe papá y mamá prefieren echarle la culpa al jabón de fregar.\nEn esta obra contaminada por las vanguardias (Vitrac militó en el movimiento dadá, y después junto a Breton y sus chicos) hay un monólogo netamente surrealista con el que Víctor deja estupefactas a sus víctimas, situaciones que anticipan el teatro del absurdo, diálogos de alta comedia, escenas minadas... Y un humor cada vez más despiadado y oscuro. Tanto que, la última frase que se pronuncia antes de bajar el telón es: '¡Esto es una tragedia!'.\nTras su estreno en 1928, Víctor permaneció semiolvidada, como la mayoría de las obras de Vitrac, hasta que Jean Anouilh llamó la atención sobre ella con su celebrado montaje de 1962. Ahora la pone en escena Joan Ollé en el Teatre Fabià Puigserver (el nuevo Lliure), de Barcelona: del 30 de enero al 10 de marzo. Ollé conoce bien el carácter del terrible niño suicida y de sus padres, bisabuelos pudientes de los Simpson, porque hace ocho años confraternizó con ellos en un taller del Institut del Teatre. Sus nuevos intérpretes son Carles Martínez, Mireia Aixalà, Pep Tosar, Rosa Renom, Maria Molins, Xicu Masó, Rosa Gàmiz, Enric Serra, Mónica López y Daniel Salgado.\n\n* Este artículo apareció en la edición impresa del Sábado, 26 de enero de 2002\n NEWSLETTER \n Recibe el boletín de Babelia \nTeléfono: 902 20 21 41\nNuestro horario de atención al cliente es de 9 a 14 los días laborables","url":"https://elpais.com/diario/2002/01/26/babelia/1012003579_850215.html","newspaper":"elpais","scraper_id":"scraper_home","id":"7d93912d-23e2-48d2-566e-69a1eff0aaa5","sentiment_analysis_obj":{"score":0,"comparative":0,"tokens":[{"value":"un","negate":false},{"value":"cumpleaños","negate":false},{"value":"minado","negate":false},{"value":"parís","negate":false},{"value":"años","negate":false},{"value":"veinte","negate":false},{"value":"antonin","negate":false},{"value":"artaud","negate":false},{"value":"y","negate":false},{"value":"roger","negate":false},{"value":"vitrac","negate":false},{"value":"socios","negate":false},{"value":"amigos","negate":false},{"value":"dentro","negate":false},{"value":"de","negate":false},{"value":"lo","negate":false},{"value":"que","negate":false},{"value":"cabe","negate":false},{"value":"y","negate":false},{"value":"rendidos","negate":false},{"value":"admiradores","negate":false},{"value":"del","negate":false},{"value":"creador","negate":false},{"value":"del","negate":false},{"value":"padre","negate":false},{"value":"ubú","negate":false},{"value":"fundan","negate":false},{"value":"el","negate":false},{"value":"théâtre","negate":false},{"value":"alfred","negate":false},{"value":"jarry","negate":false},{"value":"con","negate":false},{"value":"el","negate":false},{"value":"propósito","negate":false},{"value":"de","negate":false},{"value":"poner","negate":false},{"value":"en","negate":false},{"value":"escena","negate":false},{"value":"piezas","negate":false},{"value":"que","negate":false},{"value":"golpeen","negate":false},{"value":"al","negate":false},{"value":"espectador","negate":false},{"value":"en","negate":false},{"value":"plena","negate":false},{"value":"línea","negate":false},{"value":"de","negate":false},{"value":"flotación","negate":false},{"value":"entre","negate":false},{"value":"las","negate":false},{"value":"que","negate":false},{"value":"artaud","negate":false},{"value":"montó","negate":false},{"value":"antes","negate":false},{"value":"de","negate":false},{"value":"que","negate":false},{"value":"su","negate":false},{"value":"ideario","negate":false},{"value":"y","negate":false},{"value":"su","negate":false},{"value":"empresa","negate":false},{"value":"naufragaran","negate":false},{"value":"figura","negate":false},{"value":"víctor","negate":false},{"value":"o","negate":false},{"value":"los","negate":false},{"value":"niños","negate":false},{"value":"al","negate":false},{"value":"poder","negate":false},{"value":"tragicomedia","negate":false},{"value":"en","negate":false},{"value":"la","negate":false},{"value":"que","negate":false},{"value":"vitrac","negate":false},{"value":"esboza","negate":false},{"value":"algunas","negate":false},{"value":"de","negate":false},{"value":"las","negate":false},{"value":"claves","negate":false},{"value":"de","negate":false},{"value":"lo","negate":false},{"value":"que","negate":false},{"value":"el","negate":false},{"value":"director","negate":false},{"value":"dio","negate":false},{"value":"en","negate":false},{"value":"llamar","negate":false},{"value":"teatro","negate":false},{"value":"de","negate":false},{"value":"la","negate":false},{"value":"crueldad","negate":false},{"value":"el","negate":false},{"value":"protagonista","negate":false},{"value":"de","negate":false},{"value":"víctor","negate":false},{"value":"es","negate":false},{"value":"un","negate":false},{"value":"niño","negate":false},{"value":"extremadamente","negate":false},{"value":"precoz","negate":false},{"value":"y","negate":false},{"value":"malévolo","negate":false},{"value":"que","negate":false},{"value":"en","negate":false},{"value":"su","negate":false},{"value":"noveno","negate":false},{"value":"cumpleaños","negate":false},{"value":"decide","negate":false},{"value":"dinamitar","negate":false},{"value":"la","negate":false},{"value":"frágil","negate":false},{"value":"armonía","negate":false},{"value":"familiar","negate":false},{"value":"lo","negate":false},{"value":"primero","negate":false},{"value":"que","negate":false},{"value":"hace","negate":false},{"value":"es","negate":false},{"value":"chantajear","negate":false},{"value":"a","negate":false},{"value":"la","negate":false},{"value":"criada","negate":false},{"value":"que","negate":false},{"value":"se","negate":false},{"value":"acuesta","negate":false},{"value":"en","negate":false},{"value":"secreto","negate":false},{"value":"con","negate":false},{"value":"su","negate":false},{"value":"padre","negate":false},{"value":"para","negate":false},{"value":"que","negate":false},{"value":"le","negate":false},{"value":"conceda","negate":false},{"value":"los","negate":false},{"value":"mismos","negate":false},{"value":"favores","negate":false},{"value":"que","negate":false},{"value":"a","negate":false},{"value":"éste","negate":false},{"value":"y","negate":false},{"value":"después","negate":false},{"value":"se","negate":false},{"value":"dedica","negate":false},{"value":"a","negate":false},{"value":"sacar","negate":false},{"value":"los","negate":false},{"value":"trapos","negate":false},{"value":"sucios","negate":false},{"value":"de","negate":false},{"value":"sus","negate":false},{"value":"progenitores","negate":false},{"value":"y","negate":false},{"value":"de","negate":false},{"value":"los","negate":false},{"value":"invitados","negate":false},{"value":"a","negate":false},{"value":"su","negate":false},{"value":"fiesta","negate":false},{"value":"el","negate":false},{"value":"truco","negate":false},{"value":"lo","negate":false},{"value":"que","negate":false},{"value":"hace","negate":false},{"value":"que","negate":false},{"value":"la","negate":false},{"value":"obra","negate":false},{"value":"no","negate":true},{"value":"se","negate":false},{"value":"resuelva","negate":false},{"value":"con","negate":false},{"value":"un","negate":false},{"value":"par","negate":false},{"value":"de","negate":false},{"value":"bofetones","negate":false},{"value":"bien","negate":false},{"value":"dados","negate":false},{"value":"estriba","negate":false},{"value":"en","negate":false},{"value":"que","negate":false},{"value":"como","negate":false},{"value":"el","negate":false},{"value":"pequeño","negate":false},{"value":"nunca","negate":false},{"value":"ha","negate":false},{"value":"roto","negate":false},{"value":"un","negate":false},{"value":"plato","negate":false},{"value":"ahora","negate":false},{"value":"que","negate":false},{"value":"deja","negate":false},{"value":"caer","negate":false},{"value":"toda","negate":false},{"value":"la","negate":false},{"value":"vajilla","negate":false},{"value":"de","negate":false},{"value":"golpe","negate":false},{"value":"papá","negate":false},{"value":"y","negate":false},{"value":"mamá","negate":false},{"value":"prefieren","negate":false},{"value":"echarle","negate":false},{"value":"la","negate":false},{"value":"culpa","negate":false},{"value":"al","negate":false},{"value":"jabón","negate":false},{"value":"de","negate":false},{"value":"fregar","negate":false},{"value":"en","negate":false},{"value":"esta","negate":false},{"value":"obra","negate":false},{"value":"contaminada","negate":false},{"value":"por","negate":false},{"value":"las","negate":false},{"value":"vanguardias","negate":false},{"value":"vitrac","negate":false},{"value":"militó","negate":false},{"value":"en","negate":false},{"value":"el","negate":false},{"value":"movimiento","negate":false},{"value":"dadá","negate":false},{"value":"y","negate":false},{"value":"después","negate":false},{"value":"junto","negate":false},{"value":"a","negate":false},{"value":"breton","negate":false},{"value":"y","negate":false},{"value":"sus","negate":false},{"value":"chicos","negate":false},{"value":"hay","negate":false},{"value":"un","negate":false},{"value":"monólogo","negate":false},{"value":"netamente","negate":false},{"value":"surrealista","negate":false},{"value":"con","negate":false},{"value":"el","negate":false},{"value":"que","negate":false},{"value":"víctor","negate":false},{"value":"deja","negate":false},{"value":"estupefactas","negate":false},{"value":"a","negate":false},{"value":"sus","negate":false},{"value":"víctimas","negate":false},{"value":"situaciones","negate":false},{"value":"que","negate":false},{"value":"anticipan","negate":false},{"value":"el","negate":false},{"value":"teatro","negate":false},{"value":"del","negate":false},{"value":"absurdo","negate":false},{"value":"diálogos","negate":false},{"value":"de","negate":false},{"value":"alta","negate":false},{"value":"comedia","negate":false},{"value":"escenas","negate":false},{"value":"minadas","negate":false},{"value":"y","negate":false},{"value":"un","negate":false},{"value":"humor","negate":false},{"value":"cada","negate":false},{"value":"vez","negate":false},{"value":"más","negate":false},{"value":"despiadado","negate":false},{"value":"y","negate":false},{"value":"oscuro","negate":false},{"value":"tanto","negate":false},{"value":"que","negate":false},{"value":"la","negate":false},{"value":"última","negate":false},{"value":"frase","negate":false},{"value":"que","negate":false},{"value":"se","negate":false},{"value":"pronuncia","negate":false},{"value":"antes","negate":false},{"value":"de","negate":false},{"value":"bajar","negate":false},{"value":"el","negate":false},{"value":"telón","negate":false},{"value":"es","negate":false},{"value":"'¡esto","negate":false},{"value":"es","negate":false},{"value":"una","negate":false},{"value":"tragedia","negate":false},{"value":"'","negate":false},{"value":"tras","negate":false},{"value":"su","negate":false},{"value":"estreno","negate":false},{"value":"en","negate":false},{"value":"1928","negate":false},{"value":"víctor","negate":false},{"value":"permaneció","negate":false},{"value":"semiolvidada","negate":false},{"value":"como","negate":false},{"value":"la","negate":false},{"value":"mayoría","negate":false},{"value":"de","negate":false},{"value":"las","negate":false},{"value":"obras","negate":false},{"value":"de","negate":false},{"value":"vitrac","negate":false},{"value":"hasta","negate":false},{"value":"que","negate":false},{"value":"jean","negate":false},{"value":"anouilh","negate":false},{"value":"llamó","negate":false},{"value":"la","negate":false},{"value":"atención","negate":false},{"value":"sobre","negate":false},{"value":"ella","negate":false},{"value":"con","negate":false},{"value":"su","negate":false},{"value":"celebrado","negate":false},{"value":"montaje","negate":false},{"value":"de","negate":false},{"value":"1962","negate":false},{"value":"ahora","negate":false},{"value":"la","negate":false},{"value":"pone","negate":false},{"value":"en","negate":false},{"value":"escena","negate":false},{"value":"joan","negate":false},{"value":"ollé","negate":false},{"value":"en","negate":false},{"value":"el","negate":false},{"value":"teatre","negate":false},{"value":"fabià","negate":false},{"value":"puigserver","negate":false},{"value":"el","negate":false},{"value":"nuevo","negate":false},{"value":"lliure","negate":false},{"value":"de","negate":false},{"value":"barcelona","negate":false},{"value":"del","negate":false},{"value":"30","negate":false},{"value":"de","negate":false},{"value":"enero","negate":false},{"value":"al","negate":false},{"value":"10","negate":false},{"value":"de","negate":false},{"value":"marzo","negate":false},{"value":"ollé","negate":false},{"value":"conoce","negate":false},{"value":"bien","negate":false},{"value":"el","negate":false},{"value":"carácter","negate":false},{"value":"del","negate":false},{"value":"terrible","negate":false},{"value":"niño","negate":false},{"value":"suicida","negate":false},{"value":"y","negate":false},{"value":"de","negate":false},{"value":"sus","negate":false},{"value":"padres","negate":false},{"value":"bisabuelos","negate":false},{"value":"pudientes","negate":false},{"value":"de","negate":false},{"value":"los","negate":false},{"value":"simpson","negate":false},{"value":"porque","negate":false},{"value":"hace","negate":false},{"value":"ocho","negate":false},{"value":"años","negate":false},{"value":"confraternizó","negate":false},{"value":"con","negate":false},{"value":"ellos","negate":false},{"value":"en","negate":false},{"value":"un","negate":false},{"value":"taller","negate":false},{"value":"del","negate":false},{"value":"institut","negate":false},{"value":"del","negate":false},{"value":"teatre","negate":false},{"value":"sus","negate":false},{"value":"nuevos","negate":false},{"value":"intérpretes","negate":false},{"value":"son","negate":false},{"value":"carles","negate":false},{"value":"martínez","negate":false},{"value":"mireia","negate":false},{"value":"aixalà","negate":false},{"value":"pep","negate":false},{"value":"tosar","negate":false},{"value":"rosa","negate":false},{"value":"renom","negate":false},{"value":"maria","negate":false},{"value":"molins","negate":false},{"value":"xicu","negate":false},{"value":"masó","negate":false},{"value":"rosa","negate":false},{"value":"gàmiz","negate":false},{"value":"enric","negate":false},{"value":"serra","negate":false},{"value":"mónica","negate":false},{"value":"lópez","negate":false},{"value":"y","negate":false},{"value":"daniel","negate":false},{"value":"salgado","negate":false},{"value":"este","negate":false},{"value":"artículo","negate":false},{"value":"apareció","negate":false},{"value":"en","negate":false},{"value":"la","negate":false},{"value":"edición","negate":false},{"value":"impresa","negate":false},{"value":"del","negate":false},{"value":"sábado","negate":false},{"value":"26","negate":false},{"value":"de","negate":false},{"value":"enero","negate":false},{"value":"de","negate":false},{"value":"2002","negate":false},{"value":"newsletter","negate":false},{"value":"recibe","negate":false},{"value":"el","negate":false},{"value":"boletín","negate":false},{"value":"de","negate":false},{"value":"babelia","negate":false},{"value":"teléfono","negate":false},{"value":"902","negate":false},{"value":"20","negate":false},{"value":"21","negate":false},{"value":"41","negate":false},{"value":"nuestro","negate":false},{"value":"horario","negate":false},{"value":"de","negate":false},{"value":"atención","negate":false},{"value":"al","negate":false},{"value":"cliente","negate":false},{"value":"es","negate":false},{"value":"de","negate":false},{"value":"9","negate":false},{"value":"a","negate":false},{"value":"14","negate":false},{"value":"los","negate":false},{"value":"días","negate":false},{"value":"laborables","negate":false}],"words":["minado","víctor","crueldad","víctor","malévolo","armonía","favores","roto","golpe","culpa","víctor","víctimas","comedia","humor","frase","tragedia","víctor","celebrado","terrible","suicida","rosa","rosa"],"positive":["víctor","víctor","armonía","favores","víctor","comedia","humor","víctor","celebrado","rosa","rosa"],"negative":["minado","crueldad","malévolo","roto","golpe","culpa","víctimas","frase","tragedia","terrible","suicida"]},"sentiment_analysis_score":0,"sentiment_analysis_comparative":0}